[
  {
    "id": 1319,
    "created": 1560209653152,
    "updated": 1560209653152,
    "deleted": false,
    "modelName": "",
    "brandId": 10,
    "skuId": "LHSTATX2060030",
    "ourPrice": 122.34,
    "desc": "LT285/60R20 LIONHART LIONCLAW ATX2  125/122S",
    "quantity": ""
  },
  {
    "id": 1318,
    "created": 1560209653146,
    "updated": 1560209653146,
    "deleted": false,
    "modelName": "",
    "brandId": 10,
    "skuId": "LHSTATX2065010",
    "ourPrice": 110.37,
    "desc": "LT275/65R20 LIONHART LIONCLAW ATX2  126/123S",
    "quantity": ""
  },
  {
    "id": 1317,
    "created": 1560209653140,
    "updated": 1560209653140,
    "deleted": false,
    "modelName": "",
    "brandId": 10,
    "skuId": "LHSTATX2060020",
    "ourPrice": 98.75,
    "desc": "LT265/60R20 LIONHART LIONCLAW ATX2  121/118S",
    "quantity": ""
  },
  {
    "id": 1316,
    "created": 1560209653135,
    "updated": 1560209653135,
    "deleted": false,
    "modelName": "",
    "brandId": 10,
    "skuId": "LHSTATX2060010",
    "ourPrice": 100.78,
    "desc": "275/60R20 LIONHART LIONCLAW ATX2  119H  XL",
    "quantity": ""
  },
  {
    "id": 1315,
    "created": 1560209653129,
    "updated": 1560209653129,
    "deleted": false,
    "modelName": "",
    "brandId": 10,
    "skuId": "LHSTATX2055010",
    "ourPrice": 104.95,
    "desc": "275/55R20 LIONHART LIONCLAW ATX2  113T",
    "quantity": ""
  },
  {
    "id": 1314,
    "created": 1560209653124,
    "updated": 1560209653124,
    "deleted": false,
    "modelName": "",
    "brandId": 10,
    "skuId": "LHSTATX2050010",
    "ourPrice": 92.21,
    "desc": "265/50R20 LIONHART LIONCLAW ATX2  107T",
    "quantity": ""
  },
  {
    "id": 1313,
    "created": 1560209653118,
    "updated": 1560209653118,
    "deleted": false,
    "modelName": "",
    "brandId": 10,
    "skuId": "LHSTATX1870010",
    "ourPrice": 104.15,
    "desc": "LT275/70R18 LIONHART LIONCLAW ATX2  125/122S",
    "quantity": ""
  },
  {
    "id": 1312,
    "created": 1560209653112,
    "updated": 1560209653112,
    "deleted": false,
    "modelName": "",
    "brandId": 10,
    "skuId": "LHSTATX1865010",
    "ourPrice": 101.22,
    "desc": "LT275/65R18 LIONHART LIONCLAW ATX2  123/120S",
    "quantity": ""
  },
  {
    "id": 1311,
    "created": 1560209653106,
    "updated": 1560209653106,
    "deleted": false,
    "modelName": "",
    "brandId": 10,
    "skuId": "LHSTATX1870020",
    "ourPrice": 96.99,
    "desc": "LT265/70R18 LIONHART LIONCLAW ATX2  124/121S",
    "quantity": ""
  },
  {
    "id": 1310,
    "created": 1560209653100,
    "updated": 1560209653100,
    "deleted": false,
    "modelName": "",
    "brandId": 10,
    "skuId": "LHSTATX1770020",
    "ourPrice": 102.65,
    "desc": "LT285/70R17 LIONHART LIONCLAW ATX2  121/118Q",
    "quantity": ""
  },
  {
    "id": 1309,
    "created": 1560209653094,
    "updated": 1560209653094,
    "deleted": false,
    "modelName": "",
    "brandId": 10,
    "skuId": "LHSTATX1770010",
    "ourPrice": 85.99,
    "desc": "LT265/70R17 LIONHART LIONCLAW ATX2  121/118S",
    "quantity": ""
  },
  {
    "id": 1308,
    "created": 1560209653088,
    "updated": 1560209653088,
    "deleted": false,
    "modelName": "",
    "brandId": 10,
    "skuId": "LHSTATX1775010",
    "ourPrice": 83.18,
    "desc": "LT245/75R17 LIONHART LIONCLAW ATX2  121/118S",
    "quantity": ""
  },
  {
    "id": 1307,
    "created": 1560209653082,
    "updated": 1560209653082,
    "deleted": false,
    "modelName": "",
    "brandId": 10,
    "skuId": "LHSTATX1770030",
    "ourPrice": 81.85,
    "desc": "LT245/70R17 LIONHART LIONCLAW ATX2  119/116S",
    "quantity": ""
  },
  {
    "id": 1306,
    "created": 1560209653077,
    "updated": 1560209653077,
    "deleted": false,
    "modelName": "",
    "brandId": 10,
    "skuId": "LHSTATX1780010",
    "ourPrice": 80.99,
    "desc": "LT235/80R17 LIONHART LIONCLAW ATX2  120/117S",
    "quantity": ""
  },
  {
    "id": 1305,
    "created": 1560209653071,
    "updated": 1560209653071,
    "deleted": false,
    "modelName": "",
    "brandId": 10,
    "skuId": "LHSTATX1765010",
    "ourPrice": 90.57,
    "desc": "265/65R17 LIONHART LIONCLAW ATX2  112T",
    "quantity": ""
  },
  {
    "id": 1304,
    "created": 1560209653065,
    "updated": 1560209653065,
    "deleted": false,
    "modelName": "",
    "brandId": 10,
    "skuId": "LHSTATX1675020",
    "ourPrice": 97.35,
    "desc": "LT285/75R16 LIONHART LIONCLAW ATX2  126/123S",
    "quantity": ""
  },
  {
    "id": 1303,
    "created": 1560209653060,
    "updated": 1560209653060,
    "deleted": false,
    "modelName": "",
    "brandId": 10,
    "skuId": "LHSTATX1675010",
    "ourPrice": 78.82,
    "desc": "LT265/75R16 LIONHART LIONCLAW ATX2  123/120S",
    "quantity": ""
  },
  {
    "id": 1302,
    "created": 1560209653054,
    "updated": 1560209653054,
    "deleted": false,
    "modelName": "",
    "brandId": 10,
    "skuId": "LHSTATX1670020",
    "ourPrice": 85.15,
    "desc": "LT265/70R16 LIONHART LIONCLAW ATX2  121/118S",
    "quantity": ""
  },
  {
    "id": 1301,
    "created": 1560209653048,
    "updated": 1560209653048,
    "deleted": false,
    "modelName": "",
    "brandId": 10,
    "skuId": "LHSTATX1675040",
    "ourPrice": 74.97,
    "desc": "LT245/75R16 LIONHART LIONCLAW ATX2  120/116S",
    "quantity": ""
  },
  {
    "id": 1300,
    "created": 1560209653042,
    "updated": 1560209653042,
    "deleted": false,
    "modelName": "",
    "brandId": 10,
    "skuId": "LHSTATX1685020",
    "ourPrice": 75.4,
    "desc": "LT235/85R16 LIONHART LIONCLAW ATX2  120/116Q",
    "quantity": ""
  },
  {
    "id": 1299,
    "created": 1560209653036,
    "updated": 1560209653036,
    "deleted": false,
    "modelName": "",
    "brandId": 10,
    "skuId": "LHSTATX1670010",
    "ourPrice": 71.25,
    "desc": "LT235/70R16 LIONHART LIONCLAW ATX2  104/101S",
    "quantity": ""
  },
  {
    "id": 1298,
    "created": 1560209653031,
    "updated": 1560209653031,
    "deleted": false,
    "modelName": "",
    "brandId": 10,
    "skuId": "LHSTATX1675030",
    "ourPrice": 66.64,
    "desc": "LT225/75R16 LIONHART LIONCLAW ATX2  115/112S",
    "quantity": ""
  },
  {
    "id": 1297,
    "created": 1560209653023,
    "updated": 1560209653023,
    "deleted": false,
    "modelName": "",
    "brandId": 10,
    "skuId": "LHSTATX1685010",
    "ourPrice": 71.91,
    "desc": "LT215/85R16 LIONHART LIONCLAW ATX2  115/112S",
    "quantity": ""
  },
  {
    "id": 1296,
    "created": 1560209653017,
    "updated": 1560209653017,
    "deleted": false,
    "modelName": "",
    "brandId": 10,
    "skuId": "LHSTATX1670030",
    "ourPrice": 69.49,
    "desc": "245/70R16 LIONHART LIONCLAW ATX2  107H",
    "quantity": ""
  },
  {
    "id": 1295,
    "created": 1560209653011,
    "updated": 1560209653011,
    "deleted": false,
    "modelName": "",
    "brandId": 10,
    "skuId": "LHSTATX1575020",
    "ourPrice": 66.22,
    "desc": "LT235/75R15 LIONHART LIONCLAW ATX2  110/107S",
    "quantity": ""
  },
  {
    "id": 1294,
    "created": 1560209653005,
    "updated": 1560209653005,
    "deleted": false,
    "modelName": "",
    "brandId": 10,
    "skuId": "LHSTATX1510500",
    "ourPrice": 81.63,
    "desc": "31X10.50R15LT LIONHART LIONCLAW ATX2  109S",
    "quantity": ""
  },
  {
    "id": 1293,
    "created": 1560209652998,
    "updated": 1560209652998,
    "deleted": false,
    "modelName": "",
    "brandId": 10,
    "skuId": "LHSTATX1570020",
    "ourPrice": 69.87,
    "desc": "265/70R15 LIONHART LIONCLAW ATX2  112S",
    "quantity": ""
  },
  {
    "id": 1292,
    "created": 1560209652992,
    "updated": 1560209652992,
    "deleted": false,
    "modelName": "",
    "brandId": 10,
    "skuId": "LHSTATX1570010",
    "ourPrice": 67.13,
    "desc": "255/70R15 LIONHART LIONCLAW ATX2  108S",
    "quantity": ""
  },
  {
    "id": 1291,
    "created": 1560209652986,
    "updated": 1560209652986,
    "deleted": false,
    "modelName": "",
    "brandId": 10,
    "skuId": "LHSTATX1575010",
    "ourPrice": 56.97,
    "desc": "215/75R15 LIONHART LIONCLAW ATX2  100T",
    "quantity": ""
  },
  {
    "id": 1290,
    "created": 1560209652980,
    "updated": 1560209652980,
    "deleted": false,
    "modelName": "",
    "brandId": 10,
    "skuId": "LHSTHT2060030",
    "ourPrice": 115.76,
    "desc": "LT285/60R20 LIONHART LIONCLAW HT  125/122S",
    "quantity": ""
  },
  {
    "id": 1289,
    "created": 1560209652974,
    "updated": 1560209652974,
    "deleted": false,
    "modelName": "",
    "brandId": 10,
    "skuId": "LHSTHT2065010",
    "ourPrice": 108.98,
    "desc": "LT275/65R20 LIONHART LIONCLAW HT  126/123S",
    "quantity": ""
  },
  {
    "id": 1288,
    "created": 1560209652969,
    "updated": 1560209652969,
    "deleted": false,
    "modelName": "",
    "brandId": 10,
    "skuId": "LHSTHT2060020",
    "ourPrice": 98.74,
    "desc": "LT265/60R20 LIONHART LIONCLAW HT  121/118S",
    "quantity": ""
  },
  {
    "id": 1287,
    "created": 1560209652963,
    "updated": 1560209652963,
    "deleted": false,
    "modelName": "",
    "brandId": 10,
    "skuId": "LHSTHT2060010",
    "ourPrice": 87.23,
    "desc": "275/60R20 LIONHART LIONCLAW HT  114T",
    "quantity": ""
  },
  {
    "id": 1286,
    "created": 1560209652957,
    "updated": 1560209652957,
    "deleted": false,
    "modelName": "",
    "brandId": 10,
    "skuId": "LHSTHT2055010",
    "ourPrice": 82.41,
    "desc": "275/55R20 LIONHART LIONCLAW HT  117H",
    "quantity": ""
  },
  {
    "id": 1285,
    "created": 1560209652952,
    "updated": 1560209652952,
    "deleted": false,
    "modelName": "",
    "brandId": 10,
    "skuId": "LHSTHT1865040",
    "ourPrice": 63.82,
    "desc": "P235/65R18 LIONHART LIONCLAW HT  104T",
    "quantity": ""
  },
  {
    "id": 1284,
    "created": 1560209652946,
    "updated": 1560209652946,
    "deleted": false,
    "modelName": "",
    "brandId": 10,
    "skuId": "LHSTHT1860030",
    "ourPrice": 59.86,
    "desc": "P235/60R18 LIONHART LIONCLAW HT  102T",
    "quantity": ""
  },
  {
    "id": 1283,
    "created": 1560209652940,
    "updated": 1560209652940,
    "deleted": false,
    "modelName": "",
    "brandId": 10,
    "skuId": "LHSTHT1870020",
    "ourPrice": 92.98,
    "desc": "LT275/70R18 LIONHART LIONCLAW HT  125/122S",
    "quantity": ""
  },
  {
    "id": 1282,
    "created": 1560209652934,
    "updated": 1560209652934,
    "deleted": false,
    "modelName": "",
    "brandId": 10,
    "skuId": "LHSTHT1865030",
    "ourPrice": 94.98,
    "desc": "LT275/65R18 LIONHART LIONCLAW HT  123/120S",
    "quantity": ""
  },
  {
    "id": 1281,
    "created": 1560209652929,
    "updated": 1560209652929,
    "deleted": false,
    "modelName": "",
    "brandId": 10,
    "skuId": "LHSTHT1870010",
    "ourPrice": 94.73,
    "desc": "LT265/70R18 LIONHART LIONCLAW HT  124/121S",
    "quantity": ""
  },
  {
    "id": 1280,
    "created": 1560209652923,
    "updated": 1560209652923,
    "deleted": false,
    "modelName": "",
    "brandId": 10,
    "skuId": "LHSTHT1860010",
    "ourPrice": 65.48,
    "desc": "245/60R18 LIONHART LIONCLAW HT  105H",
    "quantity": ""
  },
  {
    "id": 1279,
    "created": 1560209652917,
    "updated": 1560209652917,
    "deleted": false,
    "modelName": "",
    "brandId": 10,
    "skuId": "LHSTHT1855010",
    "ourPrice": 63.21,
    "desc": "235/55R18 LIONHART LIONCLAW HT  104V  XL",
    "quantity": ""
  },
  {
    "id": 1278,
    "created": 1560209652911,
    "updated": 1560209652911,
    "deleted": false,
    "modelName": "",
    "brandId": 10,
    "skuId": "LHSTHT1770050",
    "ourPrice": 69.54,
    "desc": "P265/70R17 LIONHART LIONCLAW HT  113T",
    "quantity": ""
  },
  {
    "id": 1277,
    "created": 1560209652906,
    "updated": 1560209652906,
    "deleted": false,
    "modelName": "",
    "brandId": 10,
    "skuId": "LHSTHT1765060",
    "ourPrice": 65.23,
    "desc": "P265/65R17 LIONHART LIONCLAW HT  110T",
    "quantity": ""
  },
  {
    "id": 1276,
    "created": 1560209652900,
    "updated": 1560209652900,
    "deleted": false,
    "modelName": "",
    "brandId": 10,
    "skuId": "LHSTHT1765050",
    "ourPrice": 64.47,
    "desc": "P255/65R17 LIONHART LIONCLAW HT  110H",
    "quantity": ""
  },
  {
    "id": 1275,
    "created": 1560209652894,
    "updated": 1560209652894,
    "deleted": false,
    "modelName": "",
    "brandId": 10,
    "skuId": "LHSTHT1765040",
    "ourPrice": 59.74,
    "desc": "P245/65R17 LIONHART LIONCLAW HT  105T",
    "quantity": ""
  },
  {
    "id": 1274,
    "created": 1560209652888,
    "updated": 1560209652888,
    "deleted": false,
    "modelName": "",
    "brandId": 10,
    "skuId": "LHSTHT1765030",
    "ourPrice": 55.79,
    "desc": "P235/65R17 LIONHART LIONCLAW HT  103T",
    "quantity": ""
  },
  {
    "id": 1273,
    "created": 1560209652882,
    "updated": 1560209652882,
    "deleted": false,
    "modelName": "",
    "brandId": 10,
    "skuId": "LHSTHT1765020",
    "ourPrice": 53.43,
    "desc": "P225/65R17 LIONHART LIONCLAW HT  102T",
    "quantity": ""
  },
  {
    "id": 1272,
    "created": 1560209652877,
    "updated": 1560209652877,
    "deleted": false,
    "modelName": "",
    "brandId": 10,
    "skuId": "LHSTHT1765010",
    "ourPrice": 52.08,
    "desc": "P215/65R17 LIONHART LIONCLAW HT  98T",
    "quantity": ""
  },
  {
    "id": 1271,
    "created": 1560209652871,
    "updated": 1560209652871,
    "deleted": false,
    "modelName": "",
    "brandId": 10,
    "skuId": "LHSTHT1760010",
    "ourPrice": 52.56,
    "desc": "P215/60R17 LIONHART LIONCLAW HT  96H",
    "quantity": ""
  },
  {
    "id": 1270,
    "created": 1560209652864,
    "updated": 1560209652864,
    "deleted": false,
    "modelName": "",
    "brandId": 10,
    "skuId": "LHSTHT1770020",
    "ourPrice": 79.36,
    "desc": "LT265/70R17 LIONHART LIONCLAW HT  121/118Q",
    "quantity": ""
  },
  {
    "id": 1269,
    "created": 1560209652859,
    "updated": 1560209652859,
    "deleted": false,
    "modelName": "",
    "brandId": 10,
    "skuId": "LHSTHT1775010",
    "ourPrice": 83.16,
    "desc": "LT245/75R17 LIONHART LIONCLAW HT  121/118Q",
    "quantity": ""
  },
  {
    "id": 1268,
    "created": 1560209652853,
    "updated": 1560209652853,
    "deleted": false,
    "modelName": "",
    "brandId": 10,
    "skuId": "LHSTHT1770010",
    "ourPrice": 77.39,
    "desc": "LT245/70R17 LIONHART LIONCLAW HT  119/116S",
    "quantity": ""
  },
  {
    "id": 1267,
    "created": 1560209652847,
    "updated": 1560209652847,
    "deleted": false,
    "modelName": "",
    "brandId": 10,
    "skuId": "LHSTHT1780010",
    "ourPrice": 73.26,
    "desc": "LT235/80R17 LIONHART LIONCLAW HT  120/117Q",
    "quantity": ""
  },
  {
    "id": 1266,
    "created": 1560209652841,
    "updated": 1560209652841,
    "deleted": false,
    "modelName": "",
    "brandId": 10,
    "skuId": "LHSTHT1760020",
    "ourPrice": 51.57,
    "desc": "225/60R17 LIONHART LIONCLAW HT  99H",
    "quantity": ""
  },
  {
    "id": 1265,
    "created": 1560209652835,
    "updated": 1560209652835,
    "deleted": false,
    "modelName": "",
    "brandId": 10,
    "skuId": "LHSTHT1670110",
    "ourPrice": 67.07,
    "desc": "P265/70R16 LIONHART LIONCLAW HT  111T",
    "quantity": ""
  },
  {
    "id": 1264,
    "created": 1560209652828,
    "updated": 1560209652828,
    "deleted": false,
    "modelName": "",
    "brandId": 10,
    "skuId": "LHSTHT1670100",
    "ourPrice": 62.29,
    "desc": "P255/70R16 LIONHART LIONCLAW HT  109T",
    "quantity": ""
  },
  {
    "id": 1263,
    "created": 1560209652822,
    "updated": 1560209652822,
    "deleted": false,
    "modelName": "",
    "brandId": 10,
    "skuId": "LHSTHT1670090",
    "ourPrice": 59.74,
    "desc": "P245/70R16 LIONHART LIONCLAW HT  106T",
    "quantity": ""
  },
  {
    "id": 1262,
    "created": 1560209652816,
    "updated": 1560209652816,
    "deleted": false,
    "modelName": "",
    "brandId": 10,
    "skuId": "LHSTHT1670080",
    "ourPrice": 54.87,
    "desc": "P235/70R16 LIONHART LIONCLAW HT  107T",
    "quantity": ""
  },
  {
    "id": 1261,
    "created": 1560209652810,
    "updated": 1560209652810,
    "deleted": false,
    "modelName": "",
    "brandId": 10,
    "skuId": "LHSTHT1670070",
    "ourPrice": 50.98,
    "desc": "P225/70R16 LIONHART LIONCLAW HT  101T",
    "quantity": ""
  },
  {
    "id": 1260,
    "created": 1560209652804,
    "updated": 1560209652804,
    "deleted": false,
    "modelName": "",
    "brandId": 10,
    "skuId": "LHSTHT1670060",
    "ourPrice": 48.05,
    "desc": "P215/70R16 LIONHART LIONCLAW HT  99T",
    "quantity": ""
  },
  {
    "id": 1259,
    "created": 1560209652799,
    "updated": 1560209652799,
    "deleted": false,
    "modelName": "",
    "brandId": 10,
    "skuId": "LHSTHT1675010",
    "ourPrice": 77.72,
    "desc": "LT265/75R16 LIONHART LIONCLAW HT  123/120Q",
    "quantity": ""
  },
  {
    "id": 1258,
    "created": 1560209652793,
    "updated": 1560209652793,
    "deleted": false,
    "modelName": "",
    "brandId": 10,
    "skuId": "LHSTHT1675030",
    "ourPrice": 71.67,
    "desc": "LT245/75R16 LIONHART LIONCLAW HT  120/116S",
    "quantity": ""
  },
  {
    "id": 1257,
    "created": 1560209652786,
    "updated": 1560209652786,
    "deleted": false,
    "modelName": "",
    "brandId": 10,
    "skuId": "LHSTHT1685020",
    "ourPrice": 71.49,
    "desc": "LT235/85R16 LIONHART LIONCLAW HT  120/116Q",
    "quantity": ""
  },
  {
    "id": 1256,
    "created": 1560209652780,
    "updated": 1560209652780,
    "deleted": false,
    "modelName": "",
    "brandId": 10,
    "skuId": "LHSTHT1675020",
    "ourPrice": 62.68,
    "desc": "LT225/75R16 LIONHART LIONCLAW HT  115/112S",
    "quantity": ""
  },
  {
    "id": 1255,
    "created": 1560209652774,
    "updated": 1560209652774,
    "deleted": false,
    "modelName": "",
    "brandId": 10,
    "skuId": "LHSTHT1575020",
    "ourPrice": 54.85,
    "desc": "P235/75R15 LIONHART LIONCLAW HT  105T",
    "quantity": ""
  },
  {
    "id": 1254,
    "created": 1560209652768,
    "updated": 1560209652768,
    "deleted": false,
    "modelName": "",
    "brandId": 10,
    "skuId": "LHST103225010",
    "ourPrice": 491.92,
    "desc": "305/25R32 LIONHART LH-TEN  108W  XL",
    "quantity": ""
  },
  {
    "id": 1253,
    "created": 1560209652763,
    "updated": 1560209652763,
    "deleted": false,
    "modelName": "",
    "brandId": 10,
    "skuId": "LHST103020010",
    "ourPrice": 290.32,
    "desc": "315/20R30 LIONHART LH-TEN  106W  XL",
    "quantity": ""
  },
  {
    "id": 1252,
    "created": 1560209652757,
    "updated": 1560209652757,
    "deleted": false,
    "modelName": "",
    "brandId": 10,
    "skuId": "LHST103030010",
    "ourPrice": 173.74,
    "desc": "255/30R30 LIONHART LH-TEN  103W  XL",
    "quantity": ""
  },
  {
    "id": 1251,
    "created": 1560209652751,
    "updated": 1560209652751,
    "deleted": false,
    "modelName": "",
    "brandId": 10,
    "skuId": "LHST102835010",
    "ourPrice": 176.77,
    "desc": "325/35R28 LIONHART LH-TEN  120V  XL",
    "quantity": ""
  },
  {
    "id": 1250,
    "created": 1560209652745,
    "updated": 1560209652745,
    "deleted": false,
    "modelName": "",
    "brandId": 10,
    "skuId": "LHST102825010",
    "ourPrice": 146.46,
    "desc": "295/25ZR28 LIONHART LH-TEN  103W  XL",
    "quantity": ""
  },
  {
    "id": 1249,
    "created": 1560209652739,
    "updated": 1560209652739,
    "deleted": false,
    "modelName": "",
    "brandId": 10,
    "skuId": "LHST102825020",
    "ourPrice": 146.46,
    "desc": "275/25ZR28 LIONHART LH-TEN  101W  XL",
    "quantity": ""
  },
  {
    "id": 1248,
    "created": 1560209652734,
    "updated": 1560209652734,
    "deleted": false,
    "modelName": "",
    "brandId": 10,
    "skuId": "LHST102640010",
    "ourPrice": 145.45,
    "desc": "315/40R26 LIONHART LH-TEN  120V  XL",
    "quantity": ""
  },
  {
    "id": 1247,
    "created": 1560209652728,
    "updated": 1560209652728,
    "deleted": false,
    "modelName": "",
    "brandId": 10,
    "skuId": "LHST102630020",
    "ourPrice": 93.74,
    "desc": "305/30ZR26 LIONHART LH-TEN  109W  XL",
    "quantity": ""
  },
  {
    "id": 1246,
    "created": 1560209652721,
    "updated": 1560209652721,
    "deleted": false,
    "modelName": "",
    "brandId": 10,
    "skuId": "LHST102630010",
    "ourPrice": 89.43,
    "desc": "295/30ZR26 LIONHART LH-TEN  107W  XL",
    "quantity": ""
  },
  {
    "id": 1245,
    "created": 1560209652716,
    "updated": 1560209652716,
    "deleted": false,
    "modelName": "",
    "brandId": 10,
    "skuId": "LHST102625010",
    "ourPrice": 113.22,
    "desc": "275/25ZR26 LIONHART LH-TEN  98W  XL",
    "quantity": ""
  },
  {
    "id": 1244,
    "created": 1560209652709,
    "updated": 1560209652709,
    "deleted": false,
    "modelName": "",
    "brandId": 10,
    "skuId": "LHST102630030",
    "ourPrice": 115.58,
    "desc": "255/30R26 LIONHART LH-TEN  99W  XL",
    "quantity": ""
  },
  {
    "id": 1243,
    "created": 1560209652701,
    "updated": 1560209652701,
    "deleted": false,
    "modelName": "",
    "brandId": 10,
    "skuId": "LHST102435010",
    "ourPrice": 84.85,
    "desc": "305/35R24 LIONHART LH-TEN  112V  XL",
    "quantity": ""
  },
  {
    "id": 1242,
    "created": 1560209652695,
    "updated": 1560209652695,
    "deleted": false,
    "modelName": "",
    "brandId": 10,
    "skuId": "LHST102435020",
    "ourPrice": 82.83,
    "desc": "295/35R24 LIONHART LH-TEN  110V  XL",
    "quantity": ""
  },
  {
    "id": 1241,
    "created": 1560209652690,
    "updated": 1560209652690,
    "deleted": false,
    "modelName": "",
    "brandId": 10,
    "skuId": "LHST102430010",
    "ourPrice": 80.42,
    "desc": "275/30ZR24 LIONHART LH-TEN  101W  XL",
    "quantity": ""
  },
  {
    "id": 1240,
    "created": 1560209652683,
    "updated": 1560209652683,
    "deleted": false,
    "modelName": "",
    "brandId": 10,
    "skuId": "LHST102425010",
    "ourPrice": 82.22,
    "desc": "275/25ZR24 LIONHART LH-TEN  96W  XL",
    "quantity": ""
  },
  {
    "id": 1239,
    "created": 1560209652676,
    "updated": 1560209652676,
    "deleted": false,
    "modelName": "",
    "brandId": 10,
    "skuId": "LHST102225010",
    "ourPrice": 184.79,
    "desc": "335/25R22 LIONHART LH-TEN  105W  XL",
    "quantity": ""
  },
  {
    "id": 1238,
    "created": 1560209652670,
    "updated": 1560209652670,
    "deleted": false,
    "modelName": "",
    "brandId": 10,
    "skuId": "LHST102245010",
    "ourPrice": 84.17,
    "desc": "305/45R22 LIONHART LH-TEN  118V  XL",
    "quantity": ""
  },
  {
    "id": 1237,
    "created": 1560209652663,
    "updated": 1560209652663,
    "deleted": false,
    "modelName": "",
    "brandId": 10,
    "skuId": "LHST102240010",
    "ourPrice": 78.92,
    "desc": "305/40R22 LIONHART LH-TEN  114V  XL",
    "quantity": ""
  },
  {
    "id": 1236,
    "created": 1560209652657,
    "updated": 1560209652657,
    "deleted": false,
    "modelName": "",
    "brandId": 10,
    "skuId": "LHST102230010",
    "ourPrice": 96.79,
    "desc": "295/30R22 LIONHART LH-TEN  103W  XL",
    "quantity": ""
  },
  {
    "id": 1235,
    "created": 1560209652651,
    "updated": 1560209652651,
    "deleted": false,
    "modelName": "",
    "brandId": 10,
    "skuId": "LHST102245020",
    "ourPrice": 88.89,
    "desc": "285/45R22 LIONHART LH-TEN  114V  XL",
    "quantity": ""
  },
  {
    "id": 1234,
    "created": 1560209652645,
    "updated": 1560209652645,
    "deleted": false,
    "modelName": "",
    "brandId": 10,
    "skuId": "LHST102235010",
    "ourPrice": 68.57,
    "desc": "265/35ZR22 LIONHART LH-TEN  102W  XL",
    "quantity": ""
  },
  {
    "id": 1233,
    "created": 1560209652638,
    "updated": 1560209652638,
    "deleted": false,
    "modelName": "",
    "brandId": 10,
    "skuId": "LHST102050010",
    "ourPrice": 75.76,
    "desc": "285/50R20 LIONHART LH-TEN  116V  XL",
    "quantity": ""
  },
  {
    "id": 1232,
    "created": 1560209652633,
    "updated": 1560209652633,
    "deleted": false,
    "modelName": "",
    "brandId": 10,
    "skuId": "LHST102055010",
    "ourPrice": 82.41,
    "desc": "275/55R20 LIONHART LH-TEN  117V  XL",
    "quantity": ""
  },
  {
    "id": 1231,
    "created": 1560209652627,
    "updated": 1560209652627,
    "deleted": false,
    "modelName": "",
    "brandId": 10,
    "skuId": "LHST102045010",
    "ourPrice": 71.46,
    "desc": "275/45R20 LIONHART LH-TEN  110V  XL",
    "quantity": ""
  },
  {
    "id": 1230,
    "created": 1560209652621,
    "updated": 1560209652621,
    "deleted": false,
    "modelName": "",
    "brandId": 10,
    "skuId": "LHST101860010",
    "ourPrice": 75.64,
    "desc": "265/60R18 LIONHART LH-TEN  110V",
    "quantity": ""
  },
  {
    "id": 1229,
    "created": 1560209652615,
    "updated": 1560209652615,
    "deleted": false,
    "modelName": "",
    "brandId": 10,
    "skuId": "LHST101855010",
    "ourPrice": 60.84,
    "desc": "255/55R18 LIONHART LH-TEN  109W  XL",
    "quantity": ""
  },
  {
    "id": 1228,
    "created": 1560209652609,
    "updated": 1560209652609,
    "deleted": false,
    "modelName": "",
    "brandId": 10,
    "skuId": "LHST53030010",
    "ourPrice": 255.89,
    "desc": "315/30R30 LIONHART LH-FIVE",
    "quantity": ""
  },
  {
    "id": 1227,
    "created": 1560209652604,
    "updated": 1560209652604,
    "deleted": false,
    "modelName": "",
    "brandId": 10,
    "skuId": "LHST52625010",
    "ourPrice": 116.73,
    "desc": "295/25R26 LIONHART LH-FIVE",
    "quantity": ""
  },
  {
    "id": 1226,
    "created": 1560209652598,
    "updated": 1560209652598,
    "deleted": false,
    "modelName": "",
    "brandId": 10,
    "skuId": "LHST52430010",
    "ourPrice": 108.89,
    "desc": "295/30R24 LIONHART LH-FIVE  109W  XL",
    "quantity": ""
  },
  {
    "id": 1225,
    "created": 1560209652593,
    "updated": 1560209652593,
    "deleted": false,
    "modelName": "",
    "brandId": 10,
    "skuId": "LHST52425010",
    "ourPrice": 106.62,
    "desc": "295/25R24 LIONHART LH-FIVE  102W  XL",
    "quantity": ""
  },
  {
    "id": 1224,
    "created": 1560209652586,
    "updated": 1560209652586,
    "deleted": false,
    "modelName": "",
    "brandId": 10,
    "skuId": "LHST52423010",
    "ourPrice": 150,
    "desc": "295/23R24 LIONHART LH-FIVE  102W  XL",
    "quantity": ""
  },
  {
    "id": 1223,
    "created": 1560209652581,
    "updated": 1560209652581,
    "deleted": false,
    "modelName": "",
    "brandId": 10,
    "skuId": "LHST52435010",
    "ourPrice": 106.69,
    "desc": "275/35R24 LIONHART LH-FIVE  106W  XL",
    "quantity": ""
  },
  {
    "id": 1222,
    "created": 1560209652575,
    "updated": 1560209652575,
    "deleted": false,
    "modelName": "",
    "brandId": 10,
    "skuId": "LHST52423020",
    "ourPrice": 113.65,
    "desc": "275/23R24 LIONHART LH-FIVE",
    "quantity": ""
  },
  {
    "id": 1221,
    "created": 1560209652569,
    "updated": 1560209652569,
    "deleted": false,
    "modelName": "",
    "brandId": 10,
    "skuId": "LHST52430020",
    "ourPrice": 80.35,
    "desc": "255/30R24 LIONHART LH-FIVE  97W  XL",
    "quantity": ""
  },
  {
    "id": 1220,
    "created": 1560209652563,
    "updated": 1560209652563,
    "deleted": false,
    "modelName": "",
    "brandId": 10,
    "skuId": "LHST52425020",
    "ourPrice": 109.34,
    "desc": "255/25R24 LIONHART LH-FIVE  95W  XL",
    "quantity": ""
  },
  {
    "id": 1219,
    "created": 1560209652557,
    "updated": 1560209652557,
    "deleted": false,
    "modelName": "",
    "brandId": 10,
    "skuId": "LHST52225010",
    "ourPrice": 170.48,
    "desc": "315/25R22 LIONHART LH-FIVE  101W  XL",
    "quantity": ""
  },
  {
    "id": 1218,
    "created": 1560209652552,
    "updated": 1560209652552,
    "deleted": false,
    "modelName": "",
    "brandId": 10,
    "skuId": "LHST52235010",
    "ourPrice": 99.16,
    "desc": "305/35R22 LIONHART LH-FIVE  110W  XL",
    "quantity": ""
  },
  {
    "id": 1217,
    "created": 1560209652546,
    "updated": 1560209652546,
    "deleted": false,
    "modelName": "",
    "brandId": 10,
    "skuId": "LHST52230050",
    "ourPrice": 104.5,
    "desc": "305/30R22 LIONHART LH-FIVE  105Y  XL",
    "quantity": ""
  },
  {
    "id": 1216,
    "created": 1560209652540,
    "updated": 1560209652540,
    "deleted": false,
    "modelName": "",
    "brandId": 10,
    "skuId": "LHST52225040",
    "ourPrice": 104.49,
    "desc": "305/25R22 LIONHART LH-FIVE  103Y  XL",
    "quantity": ""
  },
  {
    "id": 1215,
    "created": 1560209652534,
    "updated": 1560209652534,
    "deleted": false,
    "modelName": "",
    "brandId": 10,
    "skuId": "LHST52225020",
    "ourPrice": 83.05,
    "desc": "295/25R22 LIONHART LH-FIVE  97W  XL",
    "quantity": ""
  },
  {
    "id": 1214,
    "created": 1560209652528,
    "updated": 1560209652528,
    "deleted": false,
    "modelName": "",
    "brandId": 10,
    "skuId": "LHST52240010",
    "ourPrice": 90.11,
    "desc": "285/40R22 LIONHART LH-FIVE  110V  XL",
    "quantity": ""
  },
  {
    "id": 1213,
    "created": 1560209652523,
    "updated": 1560209652523,
    "deleted": false,
    "modelName": "",
    "brandId": 10,
    "skuId": "LHST52235020",
    "ourPrice": 90.91,
    "desc": "285/35R22 LIONHART LH-FIVE  106W  XL",
    "quantity": ""
  },
  {
    "id": 1212,
    "created": 1560209652517,
    "updated": 1560209652517,
    "deleted": false,
    "modelName": "",
    "brandId": 10,
    "skuId": "LHST52225030",
    "ourPrice": 85.79,
    "desc": "285/25R22 LIONHART LH-FIVE  95W  XL",
    "quantity": ""
  },
  {
    "id": 1211,
    "created": 1560209652510,
    "updated": 1560209652510,
    "deleted": false,
    "modelName": "",
    "brandId": 10,
    "skuId": "LHST52240030",
    "ourPrice": 94.27,
    "desc": "275/40R22 LIONHART LH-FIVE  108Y",
    "quantity": ""
  },
  {
    "id": 1210,
    "created": 1560209652504,
    "updated": 1560209652504,
    "deleted": false,
    "modelName": "",
    "brandId": 10,
    "skuId": "LHST52240020",
    "ourPrice": 78.79,
    "desc": "265/40R22 LIONHART LH-FIVE  106W  XL",
    "quantity": ""
  },
  {
    "id": 1209,
    "created": 1560209652498,
    "updated": 1560209652498,
    "deleted": false,
    "modelName": "",
    "brandId": 10,
    "skuId": "LHST52230040",
    "ourPrice": 66.78,
    "desc": "265/30ZR22 LIONHART LH-FIVE  97W  XL",
    "quantity": ""
  },
  {
    "id": 1208,
    "created": 1560209652492,
    "updated": 1560209652492,
    "deleted": false,
    "modelName": "",
    "brandId": 10,
    "skuId": "LHST52230030",
    "ourPrice": 58.36,
    "desc": "255/30ZR22 LIONHART LH-FIVE  95W  XL",
    "quantity": ""
  },
  {
    "id": 1207,
    "created": 1560209652486,
    "updated": 1560209652486,
    "deleted": false,
    "modelName": "",
    "brandId": 10,
    "skuId": "LHST52230010",
    "ourPrice": 57.24,
    "desc": "245/30ZR22 LIONHART LH-FIVE  95W  XL",
    "quantity": ""
  },
  {
    "id": 1206,
    "created": 1560209652480,
    "updated": 1560209652480,
    "deleted": false,
    "modelName": "",
    "brandId": 10,
    "skuId": "LHST52230020",
    "ourPrice": 56.91,
    "desc": "235/30ZR22 LIONHART LH-FIVE  90W  XL",
    "quantity": ""
  },
  {
    "id": 1205,
    "created": 1560209652474,
    "updated": 1560209652474,
    "deleted": false,
    "modelName": "",
    "brandId": 10,
    "skuId": "LHST52140010",
    "ourPrice": 109.99,
    "desc": "295/40R21 LIONHART LH-FIVE  111W  XL",
    "quantity": ""
  },
  {
    "id": 1204,
    "created": 1560209652467,
    "updated": 1560209652467,
    "deleted": false,
    "modelName": "",
    "brandId": 10,
    "skuId": "LHST52135020",
    "ourPrice": 108.87,
    "desc": "295/35R21 LIONHART LH-FIVE  107V  XL",
    "quantity": ""
  },
  {
    "id": 1203,
    "created": 1560209652462,
    "updated": 1560209652462,
    "deleted": false,
    "modelName": "",
    "brandId": 10,
    "skuId": "LHST52130020",
    "ourPrice": 108.9,
    "desc": "285/30R21 LIONHART LH-FIVE  100W  XL",
    "quantity": ""
  },
  {
    "id": 1202,
    "created": 1560209652456,
    "updated": 1560209652456,
    "deleted": false,
    "modelName": "",
    "brandId": 10,
    "skuId": "LHST52140020",
    "ourPrice": 100.28,
    "desc": "265/40R21 LIONHART LH-FIVE  105Y  XL",
    "quantity": ""
  },
  {
    "id": 1201,
    "created": 1560209652450,
    "updated": 1560209652450,
    "deleted": false,
    "modelName": "",
    "brandId": 10,
    "skuId": "LHST52140030",
    "ourPrice": 93.15,
    "desc": "255/40R21 LIONHART LH-FIVE  102Y  XL",
    "quantity": ""
  },
  {
    "id": 1200,
    "created": 1560209652444,
    "updated": 1560209652444,
    "deleted": false,
    "modelName": "",
    "brandId": 10,
    "skuId": "LHST52130010",
    "ourPrice": 76.77,
    "desc": "255/30R21 LIONHART LH-FIVE  93W  XL",
    "quantity": ""
  },
  {
    "id": 1199,
    "created": 1560209652438,
    "updated": 1560209652438,
    "deleted": false,
    "modelName": "",
    "brandId": 10,
    "skuId": "LHST52140040",
    "ourPrice": 86.42,
    "desc": "245/40R21 LIONHART LH-FIVE  100Y",
    "quantity": ""
  },
  {
    "id": 1198,
    "created": 1560209652432,
    "updated": 1560209652432,
    "deleted": false,
    "modelName": "",
    "brandId": 10,
    "skuId": "LHST52135010",
    "ourPrice": 79.91,
    "desc": "245/35R21 LIONHART LH-FIVE  96W  XL",
    "quantity": ""
  },
  {
    "id": 1197,
    "created": 1560209652427,
    "updated": 1560209652427,
    "deleted": false,
    "modelName": "",
    "brandId": 10,
    "skuId": "LHST52025050",
    "ourPrice": 122.34,
    "desc": "345/25R20 LIONHART LH-FIVE  100Y",
    "quantity": ""
  },
  {
    "id": 1196,
    "created": 1560209652421,
    "updated": 1560209652421,
    "deleted": false,
    "modelName": "",
    "brandId": 10,
    "skuId": "LHST52025040",
    "ourPrice": 112.24,
    "desc": "325/25R20 LIONHART LH-FIVE  101Y  XL",
    "quantity": ""
  },
  {
    "id": 1195,
    "created": 1560209652415,
    "updated": 1560209652415,
    "deleted": false,
    "modelName": "",
    "brandId": 10,
    "skuId": "LHST52030080",
    "ourPrice": 106.09,
    "desc": "305/30R20 LIONHART LH-FIVE  103Y  XL",
    "quantity": ""
  },
  {
    "id": 1194,
    "created": 1560209652409,
    "updated": 1560209652409,
    "deleted": false,
    "modelName": "",
    "brandId": 10,
    "skuId": "LHST52025030",
    "ourPrice": 106,
    "desc": "305/25R20 LIONHART LH-FIVE  97W  XL",
    "quantity": ""
  },
  {
    "id": 1193,
    "created": 1560209652403,
    "updated": 1560209652403,
    "deleted": false,
    "modelName": "",
    "brandId": 10,
    "skuId": "LHST52035050",
    "ourPrice": 96.87,
    "desc": "295/35R20 LIONHART LH-FIVE  95Y  XL",
    "quantity": ""
  },
  {
    "id": 1192,
    "created": 1560209652398,
    "updated": 1560209652398,
    "deleted": false,
    "modelName": "",
    "brandId": 10,
    "skuId": "LHST52025020",
    "ourPrice": 114.38,
    "desc": "295/25R20 LIONHART LH-FIVE  95W  XL",
    "quantity": ""
  },
  {
    "id": 1191,
    "created": 1560209652392,
    "updated": 1560209652392,
    "deleted": false,
    "modelName": "",
    "brandId": 10,
    "skuId": "LHST52035060",
    "ourPrice": 80.81,
    "desc": "285/35R20 LIONHART LH-FIVE  104Y",
    "quantity": ""
  },
  {
    "id": 1190,
    "created": 1560209652386,
    "updated": 1560209652386,
    "deleted": false,
    "modelName": "",
    "brandId": 10,
    "skuId": "LHST52030090",
    "ourPrice": 73.78,
    "desc": "285/30R20 LIONHART LH-FIVE  99W  XL",
    "quantity": ""
  },
  {
    "id": 1189,
    "created": 1560209652378,
    "updated": 1560209652378,
    "deleted": false,
    "modelName": "",
    "brandId": 10,
    "skuId": "LHST52025010",
    "ourPrice": 105.03,
    "desc": "285/25R20 LIONHART LH-FIVE  93W  XL",
    "quantity": ""
  },
  {
    "id": 1188,
    "created": 1560209652371,
    "updated": 1560209652371,
    "deleted": false,
    "modelName": "",
    "brandId": 10,
    "skuId": "LHST52040020",
    "ourPrice": 69.96,
    "desc": "275/40R20 LIONHART LH-FIVE  106W  XL",
    "quantity": ""
  },
  {
    "id": 1187,
    "created": 1560209652365,
    "updated": 1560209652365,
    "deleted": false,
    "modelName": "",
    "brandId": 10,
    "skuId": "LHST52035070",
    "ourPrice": 66.11,
    "desc": "275/35R20 LIONHART LH-FIVE  102W  XL",
    "quantity": ""
  },
  {
    "id": 1186,
    "created": 1560209652359,
    "updated": 1560209652359,
    "deleted": false,
    "modelName": "",
    "brandId": 10,
    "skuId": "LHST52030050",
    "ourPrice": 61.41,
    "desc": "275/30R20 LIONHART LH-FIVE  97W  XL",
    "quantity": ""
  },
  {
    "id": 1185,
    "created": 1560209652352,
    "updated": 1560209652352,
    "deleted": false,
    "modelName": "",
    "brandId": 10,
    "skuId": "LHST52045030",
    "ourPrice": 64.89,
    "desc": "265/45R20 LIONHART LH-FIVE  104W",
    "quantity": ""
  },
  {
    "id": 1184,
    "created": 1560209652346,
    "updated": 1560209652346,
    "deleted": false,
    "modelName": "",
    "brandId": 10,
    "skuId": "LHST52040030",
    "ourPrice": 87.01,
    "desc": "265/40R20 LIONHART LH-FIVE  99W  XL",
    "quantity": ""
  },
  {
    "id": 1183,
    "created": 1560209652340,
    "updated": 1560209652340,
    "deleted": false,
    "modelName": "",
    "brandId": 10,
    "skuId": "LHST52030070",
    "ourPrice": 66.21,
    "desc": "265/30R20 LIONHART LH-FIVE  94Y  XL",
    "quantity": ""
  },
  {
    "id": 1182,
    "created": 1560209652334,
    "updated": 1560209652334,
    "deleted": false,
    "modelName": "",
    "brandId": 10,
    "skuId": "LHST52045020",
    "ourPrice": 70.71,
    "desc": "255/45R20 LIONHART LH-FIVE  105W  XL",
    "quantity": ""
  },
  {
    "id": 1181,
    "created": 1560209652328,
    "updated": 1560209652328,
    "deleted": false,
    "modelName": "",
    "brandId": 10,
    "skuId": "LHST52040010",
    "ourPrice": 70.71,
    "desc": "255/40R20 LIONHART LH-FIVE  101W  XL",
    "quantity": ""
  },
  {
    "id": 1180,
    "created": 1560209652323,
    "updated": 1560209652323,
    "deleted": false,
    "modelName": "",
    "brandId": 10,
    "skuId": "LHST52035080",
    "ourPrice": 56.23,
    "desc": "255/35ZR20 LIONHART LH-FIVE  97W  XL",
    "quantity": ""
  },
  {
    "id": 1179,
    "created": 1560209652317,
    "updated": 1560209652317,
    "deleted": false,
    "modelName": "",
    "brandId": 10,
    "skuId": "LHST52030030",
    "ourPrice": 81.4,
    "desc": "255/30R20 LIONHART LH-FIVE  92W  XL",
    "quantity": ""
  },
  {
    "id": 1178,
    "created": 1560209652311,
    "updated": 1560209652311,
    "deleted": false,
    "modelName": "",
    "brandId": 10,
    "skuId": "LHST52050010",
    "ourPrice": 71.72,
    "desc": "245/50R20 LIONHART LH-FIVE  102W",
    "quantity": ""
  },
  {
    "id": 1177,
    "created": 1560209652305,
    "updated": 1560209652305,
    "deleted": false,
    "modelName": "",
    "brandId": 10,
    "skuId": "LHST52045010",
    "ourPrice": 67.88,
    "desc": "245/45R20 LIONHART LH-FIVE  103W  XL",
    "quantity": ""
  },
  {
    "id": 1176,
    "created": 1560209652299,
    "updated": 1560209652299,
    "deleted": false,
    "modelName": "",
    "brandId": 10,
    "skuId": "LHST52040040",
    "ourPrice": 62.63,
    "desc": "245/40R20 LIONHART LH-FIVE  99W  LX",
    "quantity": ""
  },
  {
    "id": 1175,
    "created": 1560209652293,
    "updated": 1560209652293,
    "deleted": false,
    "modelName": "",
    "brandId": 10,
    "skuId": "LHST52035040",
    "ourPrice": 47.4,
    "desc": "245/35R20 LIONHART LH-FIVE  95W  XL",
    "quantity": ""
  },
  {
    "id": 1174,
    "created": 1560209652287,
    "updated": 1560209652287,
    "deleted": false,
    "modelName": "",
    "brandId": 10,
    "skuId": "LHST52030010",
    "ourPrice": 62.85,
    "desc": "245/30R20 LIONHART LH-FIVE  97W  XL",
    "quantity": ""
  },
  {
    "id": 1173,
    "created": 1560209652281,
    "updated": 1560209652281,
    "deleted": false,
    "modelName": "",
    "brandId": 10,
    "skuId": "LHST52035030",
    "ourPrice": 51.18,
    "desc": "235/35R20 LIONHART LH-FIVE  92W  XL",
    "quantity": ""
  },
  {
    "id": 1172,
    "created": 1560209652275,
    "updated": 1560209652275,
    "deleted": false,
    "modelName": "",
    "brandId": 10,
    "skuId": "LHST52030020",
    "ourPrice": 51.18,
    "desc": "235/30R20 LIONHART LH-FIVE  88W  XL",
    "quantity": ""
  },
  {
    "id": 1171,
    "created": 1560209652270,
    "updated": 1560209652270,
    "deleted": false,
    "modelName": "",
    "brandId": 10,
    "skuId": "LHST52035020",
    "ourPrice": 47.74,
    "desc": "225/35R20 LIONHART LH-FIVE  93W  XL",
    "quantity": ""
  },
  {
    "id": 1170,
    "created": 1560209652263,
    "updated": 1560209652263,
    "deleted": false,
    "modelName": "",
    "brandId": 10,
    "skuId": "LHST52030060",
    "ourPrice": 54.21,
    "desc": "225/30R20 LIONHART LH-FIVE  85W  XL",
    "quantity": ""
  },
  {
    "id": 1169,
    "created": 1560209652258,
    "updated": 1560209652258,
    "deleted": false,
    "modelName": "",
    "brandId": 10,
    "skuId": "LHST52035010",
    "ourPrice": 47.3,
    "desc": "215/35R20 LIONHART LH-FIVE  86W  XL",
    "quantity": ""
  },
  {
    "id": 1168,
    "created": 1560209652251,
    "updated": 1560209652251,
    "deleted": false,
    "modelName": "",
    "brandId": 10,
    "skuId": "LHST52030040",
    "ourPrice": 50.59,
    "desc": "215/30R20 LIONHART LH-FIVE  82W  XL",
    "quantity": ""
  },
  {
    "id": 1167,
    "created": 1560209652245,
    "updated": 1560209652245,
    "deleted": false,
    "modelName": "",
    "brandId": 10,
    "skuId": "LHST51945030",
    "ourPrice": 79.8,
    "desc": "275/45R19 LIONHART LH-FIVE  108V  XL",
    "quantity": ""
  },
  {
    "id": 1166,
    "created": 1560209652239,
    "updated": 1560209652239,
    "deleted": false,
    "modelName": "",
    "brandId": 10,
    "skuId": "LHST51940040",
    "ourPrice": 72.73,
    "desc": "275/40R19 LIONHART LH-FIVE  105W  XL",
    "quantity": ""
  },
  {
    "id": 1165,
    "created": 1560209652233,
    "updated": 1560209652233,
    "deleted": false,
    "modelName": "",
    "brandId": 10,
    "skuId": "LHST51935030",
    "ourPrice": 76.77,
    "desc": "275/35R19 LIONHART LH-FIVE  100W  XL",
    "quantity": ""
  },
  {
    "id": 1164,
    "created": 1560209652227,
    "updated": 1560209652227,
    "deleted": false,
    "modelName": "",
    "brandId": 10,
    "skuId": "LHST51930030",
    "ourPrice": 59.35,
    "desc": "275/30R19 LIONHART LH-FIVE  96W  XL",
    "quantity": ""
  },
  {
    "id": 1163,
    "created": 1560209652221,
    "updated": 1560209652221,
    "deleted": false,
    "modelName": "",
    "brandId": 10,
    "skuId": "LHST51935060",
    "ourPrice": 93.34,
    "desc": "265/35R19 LIONHART LH-FIVE  97W  XL",
    "quantity": ""
  },
  {
    "id": 1162,
    "created": 1560209652215,
    "updated": 1560209652215,
    "deleted": false,
    "modelName": "",
    "brandId": 10,
    "skuId": "LHST51930020",
    "ourPrice": 55.99,
    "desc": "265/30R19 LIONHART LH-FIVE  93W  XL",
    "quantity": ""
  },
  {
    "id": 1161,
    "created": 1560209652209,
    "updated": 1560209652209,
    "deleted": false,
    "modelName": "",
    "brandId": 10,
    "skuId": "LHST51960010",
    "ourPrice": 85.77,
    "desc": "255/60R19 LIONHART LH-FIVE  109H",
    "quantity": ""
  },
  {
    "id": 1160,
    "created": 1560209652203,
    "updated": 1560209652203,
    "deleted": false,
    "modelName": "",
    "brandId": 10,
    "skuId": "LHST51955010",
    "ourPrice": 78.79,
    "desc": "255/55R19 LIONHART LH-FIVE  111V  XL",
    "quantity": ""
  },
  {
    "id": 1159,
    "created": 1560209652198,
    "updated": 1560209652198,
    "deleted": false,
    "modelName": "",
    "brandId": 10,
    "skuId": "LHST51950010",
    "ourPrice": 92.76,
    "desc": "255/50R19 LIONHART LH-FIVE  103W",
    "quantity": ""
  },
  {
    "id": 1158,
    "created": 1560209652192,
    "updated": 1560209652192,
    "deleted": false,
    "modelName": "",
    "brandId": 10,
    "skuId": "LHST51940030",
    "ourPrice": 70.51,
    "desc": "255/40R19 LIONHART LH-FIVE  100W  XL",
    "quantity": ""
  },
  {
    "id": 1157,
    "created": 1560209652186,
    "updated": 1560209652186,
    "deleted": false,
    "modelName": "",
    "brandId": 10,
    "skuId": "LHST51935010",
    "ourPrice": 71.49,
    "desc": "255/35R19 LIONHART LH-FIVE  96W  XL",
    "quantity": ""
  },
  {
    "id": 1156,
    "created": 1560209652181,
    "updated": 1560209652181,
    "deleted": false,
    "modelName": "",
    "brandId": 10,
    "skuId": "LHST51930010",
    "ourPrice": 64.53,
    "desc": "255/30R19 LIONHART LH-FIVE  91W  XL",
    "quantity": ""
  },
  {
    "id": 1155,
    "created": 1560209652175,
    "updated": 1560209652175,
    "deleted": false,
    "modelName": "",
    "brandId": 10,
    "skuId": "LHST51945020",
    "ourPrice": 67.74,
    "desc": "245/45R19 LIONHART LH-FIVE  102W  XL",
    "quantity": ""
  },
  {
    "id": 1154,
    "created": 1560209652169,
    "updated": 1560209652169,
    "deleted": false,
    "modelName": "",
    "brandId": 10,
    "skuId": "LHST51940020",
    "ourPrice": 66.7,
    "desc": "245/40R19 LIONHART LH-FIVE  98W  XL",
    "quantity": ""
  },
  {
    "id": 1153,
    "created": 1560209652164,
    "updated": 1560209652164,
    "deleted": false,
    "modelName": "",
    "brandId": 10,
    "skuId": "LHST51935040",
    "ourPrice": 53.54,
    "desc": "245/35R19 LIONHART LH-FIVE  97W  XL",
    "quantity": ""
  },
  {
    "id": 1152,
    "created": 1560209652158,
    "updated": 1560209652158,
    "deleted": false,
    "modelName": "",
    "brandId": 10,
    "skuId": "LHST51935050",
    "ourPrice": 58.47,
    "desc": "235/35R19 LIONHART LH-FIVE  91W  XL",
    "quantity": ""
  },
  {
    "id": 1151,
    "created": 1560209652152,
    "updated": 1560209652152,
    "deleted": false,
    "modelName": "",
    "brandId": 10,
    "skuId": "LHST51945010",
    "ourPrice": 63.03,
    "desc": "225/45R19 LIONHART LH-FIVE  96W  XL",
    "quantity": ""
  },
  {
    "id": 1150,
    "created": 1560209652146,
    "updated": 1560209652146,
    "deleted": false,
    "modelName": "",
    "brandId": 10,
    "skuId": "LHST51940010",
    "ourPrice": 61.72,
    "desc": "225/40R19 LIONHART LH-FIVE  93W  XL",
    "quantity": ""
  },
  {
    "id": 1149,
    "created": 1560209652140,
    "updated": 1560209652140,
    "deleted": false,
    "modelName": "",
    "brandId": 10,
    "skuId": "LHST51935020",
    "ourPrice": 55.89,
    "desc": "225/35R19 LIONHART LH-FIVE  88W  XL",
    "quantity": ""
  },
  {
    "id": 1148,
    "created": 1560209652134,
    "updated": 1560209652134,
    "deleted": false,
    "modelName": "",
    "brandId": 10,
    "skuId": "LHST51835010",
    "ourPrice": 76.58,
    "desc": "285/35R18 LIONHART LH-FIVE  101W  XL",
    "quantity": ""
  },
  {
    "id": 1147,
    "created": 1560209652129,
    "updated": 1560209652129,
    "deleted": false,
    "modelName": "",
    "brandId": 10,
    "skuId": "LHST51840010",
    "ourPrice": 63.01,
    "desc": "255/40R18 LIONHART LH-FIVE  99W  XL",
    "quantity": ""
  },
  {
    "id": 1146,
    "created": 1560209652123,
    "updated": 1560209652123,
    "deleted": false,
    "modelName": "",
    "brandId": 10,
    "skuId": "LHST51845010",
    "ourPrice": 46.29,
    "desc": "225/45ZR18 LIONHART LH-FIVE  95W  XL",
    "quantity": ""
  },
  {
    "id": 1145,
    "created": 1560209652117,
    "updated": 1560209652117,
    "deleted": false,
    "modelName": "",
    "brandId": 10,
    "skuId": "LHST51755010",
    "ourPrice": 81.07,
    "desc": "275/55R17 LIONHART LH-FIVE  109V",
    "quantity": ""
  },
  {
    "id": 1144,
    "created": 1560209652111,
    "updated": 1560209652111,
    "deleted": false,
    "modelName": "",
    "brandId": 10,
    "skuId": "LHST51740010",
    "ourPrice": 51.74,
    "desc": "245/40R17 LIONHART LH-FIVE  95W  XL",
    "quantity": ""
  },
  {
    "id": 1143,
    "created": 1560209652105,
    "updated": 1560209652105,
    "deleted": false,
    "modelName": "",
    "brandId": 10,
    "skuId": "LHST51745010",
    "ourPrice": 39.18,
    "desc": "225/45R17 LIONHART LH-FIVE  94W  XL",
    "quantity": ""
  },
  {
    "id": 1142,
    "created": 1560209652100,
    "updated": 1560209652100,
    "deleted": false,
    "modelName": "",
    "brandId": 10,
    "skuId": "LHST5031945010",
    "ourPrice": 58.46,
    "desc": "235/45ZR19 LIONHART LH-503  99W  XL",
    "quantity": ""
  },
  {
    "id": 1141,
    "created": 1560209652094,
    "updated": 1560209652094,
    "deleted": false,
    "modelName": "",
    "brandId": 10,
    "skuId": "LHST5031835040",
    "ourPrice": 76.58,
    "desc": "285/35ZR18 LIONHART LH-503  101W  XL",
    "quantity": ""
  },
  {
    "id": 1140,
    "created": 1560209652089,
    "updated": 1560209652089,
    "deleted": false,
    "modelName": "",
    "brandId": 10,
    "skuId": "LHST5031835030",
    "ourPrice": 57.82,
    "desc": "265/35ZR18 LIONHART LH-503  97W  XL",
    "quantity": ""
  },
  {
    "id": 1139,
    "created": 1560209652082,
    "updated": 1560209652082,
    "deleted": false,
    "modelName": "",
    "brandId": 10,
    "skuId": "LHST5031855010",
    "ourPrice": 60.84,
    "desc": "255/55ZR18 LIONHART LH-503  109V  XL",
    "quantity": ""
  },
  {
    "id": 1138,
    "created": 1560209652077,
    "updated": 1560209652077,
    "deleted": false,
    "modelName": "",
    "brandId": 10,
    "skuId": "LHST5031845020",
    "ourPrice": 57.32,
    "desc": "255/45ZR18 LIONHART LH-503  99W",
    "quantity": ""
  },
  {
    "id": 1137,
    "created": 1560209652071,
    "updated": 1560209652071,
    "deleted": false,
    "modelName": "",
    "brandId": 10,
    "skuId": "LHST5031835020",
    "ourPrice": 55.24,
    "desc": "255/35ZR18 LIONHART LH-503  94W  XL",
    "quantity": ""
  },
  {
    "id": 1136,
    "created": 1560209652065,
    "updated": 1560209652065,
    "deleted": false,
    "modelName": "",
    "brandId": 10,
    "skuId": "LHST5031845010",
    "ourPrice": 51.49,
    "desc": "245/45ZR18 LIONHART LH-503  100W  XL",
    "quantity": ""
  },
  {
    "id": 1135,
    "created": 1560209652059,
    "updated": 1560209652059,
    "deleted": false,
    "modelName": "",
    "brandId": 10,
    "skuId": "LHST5031840020",
    "ourPrice": 45.45,
    "desc": "245/40R18 LIONHART LH-503  97W  XL",
    "quantity": ""
  },
  {
    "id": 1134,
    "created": 1560209652054,
    "updated": 1560209652054,
    "deleted": false,
    "modelName": "",
    "brandId": 10,
    "skuId": "LHST5031850010",
    "ourPrice": 53.64,
    "desc": "235/50ZR18 LIONHART LH-503  101W  XL",
    "quantity": ""
  },
  {
    "id": 1133,
    "created": 1560209652048,
    "updated": 1560209652048,
    "deleted": false,
    "modelName": "",
    "brandId": 10,
    "skuId": "LHST5031845040",
    "ourPrice": 50.54,
    "desc": "235/45ZR18 LIONHART LH-503  98W  XL",
    "quantity": ""
  },
  {
    "id": 1132,
    "created": 1560209652042,
    "updated": 1560209652042,
    "deleted": false,
    "modelName": "",
    "brandId": 10,
    "skuId": "LHST5031840030",
    "ourPrice": 43.02,
    "desc": "235/40ZR18 LIONHART LH-503  95W  XL",
    "quantity": ""
  },
  {
    "id": 1131,
    "created": 1560209652036,
    "updated": 1560209652036,
    "deleted": false,
    "modelName": "",
    "brandId": 10,
    "skuId": "LHST5031860010",
    "ourPrice": 53.72,
    "desc": "225/60ZR18 LIONHART LH-503  104V  XL",
    "quantity": ""
  },
  {
    "id": 1130,
    "created": 1560209652030,
    "updated": 1560209652030,
    "deleted": false,
    "modelName": "",
    "brandId": 10,
    "skuId": "LHST5031855030",
    "ourPrice": 54.01,
    "desc": "225/55ZR18 LIONHART LH-503  102W  XL",
    "quantity": ""
  },
  {
    "id": 1129,
    "created": 1560209652025,
    "updated": 1560209652025,
    "deleted": false,
    "modelName": "",
    "brandId": 10,
    "skuId": "LHST5031840010",
    "ourPrice": 40.96,
    "desc": "225/40ZR18 LIONHART LH-503  92W  XL",
    "quantity": ""
  },
  {
    "id": 1128,
    "created": 1560209652019,
    "updated": 1560209652019,
    "deleted": false,
    "modelName": "",
    "brandId": 10,
    "skuId": "LHST5031855020",
    "ourPrice": 49.48,
    "desc": "215/55R18 LIONHART LH-503  95V",
    "quantity": ""
  },
  {
    "id": 1127,
    "created": 1560209652013,
    "updated": 1560209652013,
    "deleted": false,
    "modelName": "",
    "brandId": 10,
    "skuId": "LHST5031845030",
    "ourPrice": 43.81,
    "desc": "215/45ZR18 LIONHART LH-503  89W",
    "quantity": ""
  },
  {
    "id": 1126,
    "created": 1560209652007,
    "updated": 1560209652007,
    "deleted": false,
    "modelName": "",
    "brandId": 10,
    "skuId": "LHST5031840040",
    "ourPrice": 42.27,
    "desc": "215/40ZR18 LIONHART LH-503  89W  XL",
    "quantity": ""
  },
  {
    "id": 1125,
    "created": 1560209652000,
    "updated": 1560209652000,
    "deleted": false,
    "modelName": "",
    "brandId": 10,
    "skuId": "LHST5031745040",
    "ourPrice": 45.45,
    "desc": "245/45ZR17 LIONHART LH-503  99W  XL",
    "quantity": ""
  },
  {
    "id": 1124,
    "created": 1560209651994,
    "updated": 1560209651994,
    "deleted": false,
    "modelName": "",
    "brandId": 10,
    "skuId": "LHST5031745030",
    "ourPrice": 42.59,
    "desc": "235/45ZR17 LIONHART LH-503  97W  XL",
    "quantity": ""
  },
  {
    "id": 1123,
    "created": 1560209651988,
    "updated": 1560209651988,
    "deleted": false,
    "modelName": "",
    "brandId": 10,
    "skuId": "LHST5031755020",
    "ourPrice": 46.05,
    "desc": "225/55ZR17 LIONHART LH-503  101W  XL",
    "quantity": ""
  },
  {
    "id": 1122,
    "created": 1560209651982,
    "updated": 1560209651982,
    "deleted": false,
    "modelName": "",
    "brandId": 10,
    "skuId": "LHST5031750020",
    "ourPrice": 44.51,
    "desc": "225/50ZR17 LIONHART LH-503  98W  XL",
    "quantity": ""
  },
  {
    "id": 1121,
    "created": 1560209651976,
    "updated": 1560209651976,
    "deleted": false,
    "modelName": "",
    "brandId": 10,
    "skuId": "LHST5031745020",
    "ourPrice": 39.18,
    "desc": "225/45ZR17 LIONHART LH-503  94W  XL",
    "quantity": ""
  },
  {
    "id": 1120,
    "created": 1560209651971,
    "updated": 1560209651971,
    "deleted": false,
    "modelName": "",
    "brandId": 10,
    "skuId": "LHST5031755010",
    "ourPrice": 43.63,
    "desc": "215/55ZR17 LIONHART LH-503  98W  XL",
    "quantity": ""
  },
  {
    "id": 1119,
    "created": 1560209651965,
    "updated": 1560209651965,
    "deleted": false,
    "modelName": "",
    "brandId": 10,
    "skuId": "LHST5031750010",
    "ourPrice": 42.29,
    "desc": "215/50ZR17 LIONHART LH-503  95W  XL",
    "quantity": ""
  },
  {
    "id": 1118,
    "created": 1560209651960,
    "updated": 1560209651960,
    "deleted": false,
    "modelName": "",
    "brandId": 10,
    "skuId": "LHST5031745010",
    "ourPrice": 37.08,
    "desc": "215/45ZR17 LIONHART LH-503  91W  XL",
    "quantity": ""
  },
  {
    "id": 1117,
    "created": 1560209651954,
    "updated": 1560209651954,
    "deleted": false,
    "modelName": "",
    "brandId": 10,
    "skuId": "LHST5031835010",
    "ourPrice": 38.41,
    "desc": "215/35ZR18 LIONHART LH-503  84W  XL",
    "quantity": ""
  },
  {
    "id": 1116,
    "created": 1560209651948,
    "updated": 1560209651948,
    "deleted": false,
    "modelName": "",
    "brandId": 10,
    "skuId": "LHST5031745050",
    "ourPrice": 37.07,
    "desc": "205/45ZR17 LIONHART LH-503  88W  XL",
    "quantity": ""
  },
  {
    "id": 1115,
    "created": 1560209651942,
    "updated": 1560209651942,
    "deleted": false,
    "modelName": "",
    "brandId": 10,
    "skuId": "LHST5031740010",
    "ourPrice": 34.79,
    "desc": "205/40ZR17 LIONHART LH-503  84W  XL",
    "quantity": ""
  },
  {
    "id": 1114,
    "created": 1560209651937,
    "updated": 1560209651937,
    "deleted": false,
    "modelName": "",
    "brandId": 10,
    "skuId": "LHST5011655030",
    "ourPrice": 40.17,
    "desc": "225/55R16 LIONHART LH-501  99W  XL",
    "quantity": ""
  },
  {
    "id": 1113,
    "created": 1560209651931,
    "updated": 1560209651931,
    "deleted": false,
    "modelName": "",
    "brandId": 10,
    "skuId": "LHST5011660030",
    "ourPrice": 40.67,
    "desc": "225/60R16 LIONHART LH-501  98H",
    "quantity": ""
  },
  {
    "id": 1112,
    "created": 1560209651925,
    "updated": 1560209651925,
    "deleted": false,
    "modelName": "",
    "brandId": 10,
    "skuId": "LHST5011665020",
    "ourPrice": 43.43,
    "desc": "215/65R16 LIONHART LH-501  98H",
    "quantity": ""
  },
  {
    "id": 1111,
    "created": 1560209651919,
    "updated": 1560209651919,
    "deleted": false,
    "modelName": "",
    "brandId": 10,
    "skuId": "LHST5011660020",
    "ourPrice": 38.6,
    "desc": "215/60R16 LIONHART LH-501  95V",
    "quantity": ""
  },
  {
    "id": 1110,
    "created": 1560209651913,
    "updated": 1560209651913,
    "deleted": false,
    "modelName": "",
    "brandId": 10,
    "skuId": "LHST5011655020",
    "ourPrice": 41.31,
    "desc": "215/55R16 LIONHART LH-501  97V  XL",
    "quantity": ""
  },
  {
    "id": 1109,
    "created": 1560209651907,
    "updated": 1560209651907,
    "deleted": false,
    "modelName": "",
    "brandId": 10,
    "skuId": "LHST5011665010",
    "ourPrice": 40.06,
    "desc": "205/65R16 LIONHART LH-501  95V",
    "quantity": ""
  },
  {
    "id": 1108,
    "created": 1560209651901,
    "updated": 1560209651901,
    "deleted": false,
    "modelName": "",
    "brandId": 10,
    "skuId": "LHST5011660010",
    "ourPrice": 35.15,
    "desc": "205/60R16 LIONHART LH-501  92V",
    "quantity": ""
  },
  {
    "id": 1107,
    "created": 1560209651895,
    "updated": 1560209651895,
    "deleted": false,
    "modelName": "",
    "brandId": 10,
    "skuId": "LHST5011655010",
    "ourPrice": 35.16,
    "desc": "205/55R16 LIONHART LH-501  91V",
    "quantity": ""
  },
  {
    "id": 1106,
    "created": 1560209651889,
    "updated": 1560209651889,
    "deleted": false,
    "modelName": "",
    "brandId": 10,
    "skuId": "LHST5011650010",
    "ourPrice": 37.2,
    "desc": "205/50R16 LIONHART LH-501  87W",
    "quantity": ""
  },
  {
    "id": 1105,
    "created": 1560209651883,
    "updated": 1560209651883,
    "deleted": false,
    "modelName": "",
    "brandId": 10,
    "skuId": "LHST5011645010",
    "ourPrice": 32.68,
    "desc": "205/45ZR16 LIONHART LH-501  87W  XL",
    "quantity": ""
  },
  {
    "id": 1104,
    "created": 1560209651877,
    "updated": 1560209651877,
    "deleted": false,
    "modelName": "",
    "brandId": 10,
    "skuId": "LHST5011655040",
    "ourPrice": 36.46,
    "desc": "195/55R16 LIONHART LH-501  87H",
    "quantity": ""
  },
  {
    "id": 1103,
    "created": 1560209651871,
    "updated": 1560209651871,
    "deleted": false,
    "modelName": "",
    "brandId": 10,
    "skuId": "LHST5011655050",
    "ourPrice": 34.01,
    "desc": "185/55R16 LIONHART LH-501  83V",
    "quantity": ""
  },
  {
    "id": 1102,
    "created": 1560209651865,
    "updated": 1560209651865,
    "deleted": false,
    "modelName": "",
    "brandId": 10,
    "skuId": "LHST5011565040",
    "ourPrice": 40.14,
    "desc": "215/65R15 LIONHART LH-501  100H  XL",
    "quantity": ""
  },
  {
    "id": 1101,
    "created": 1560209651859,
    "updated": 1560209651859,
    "deleted": false,
    "modelName": "",
    "brandId": 10,
    "skuId": "LHST5011565030",
    "ourPrice": 36.16,
    "desc": "205/65R15 LIONHART LH-501  94H",
    "quantity": ""
  },
  {
    "id": 1100,
    "created": 1560209651853,
    "updated": 1560209651853,
    "deleted": false,
    "modelName": "",
    "brandId": 10,
    "skuId": "LHST5011560030",
    "ourPrice": 35.11,
    "desc": "205/60R15 LIONHART LH-501  91V",
    "quantity": ""
  },
  {
    "id": 1099,
    "created": 1560209651847,
    "updated": 1560209651847,
    "deleted": false,
    "modelName": "",
    "brandId": 10,
    "skuId": "LHST5011565020",
    "ourPrice": 33.97,
    "desc": "195/65R15 LIONHART LH-501  91V",
    "quantity": ""
  },
  {
    "id": 1098,
    "created": 1560209651841,
    "updated": 1560209651841,
    "deleted": false,
    "modelName": "",
    "brandId": 10,
    "skuId": "LHST5011560020",
    "ourPrice": 31.2,
    "desc": "195/60R15 LIONHART LH-501  88V",
    "quantity": ""
  },
  {
    "id": 1097,
    "created": 1560209651835,
    "updated": 1560209651835,
    "deleted": false,
    "modelName": "",
    "brandId": 10,
    "skuId": "LHST5011565010",
    "ourPrice": 31.4,
    "desc": "185/65R15 LIONHART LH-501  88H",
    "quantity": ""
  },
  {
    "id": 1096,
    "created": 1560209651830,
    "updated": 1560209651830,
    "deleted": false,
    "modelName": "",
    "brandId": 10,
    "skuId": "LHST5011560010",
    "ourPrice": 31.14,
    "desc": "185/60R15 LIONHART LH-501  84H",
    "quantity": ""
  },
  {
    "id": 1095,
    "created": 1560209651824,
    "updated": 1560209651824,
    "deleted": false,
    "modelName": "",
    "brandId": 10,
    "skuId": "LHST5011555010",
    "ourPrice": 31.7,
    "desc": "185/55R15 LIONHART LH-501  82V",
    "quantity": ""
  },
  {
    "id": 1094,
    "created": 1560209651814,
    "updated": 1560209651814,
    "deleted": false,
    "modelName": "",
    "brandId": 10,
    "skuId": "LHST5011470030",
    "ourPrice": 34.34,
    "desc": "205/70R14 LIONHART LH-501  98H  XL",
    "quantity": ""
  },
  {
    "id": 1093,
    "created": 1560209651808,
    "updated": 1560209651808,
    "deleted": false,
    "modelName": "",
    "brandId": 10,
    "skuId": "LHST5011470020",
    "ourPrice": 32.81,
    "desc": "195/70R14 LIONHART LH-501  91H",
    "quantity": ""
  },
  {
    "id": 1092,
    "created": 1560209651803,
    "updated": 1560209651803,
    "deleted": false,
    "modelName": "",
    "brandId": 10,
    "skuId": "LHST5011460020",
    "ourPrice": 31.93,
    "desc": "195/60R14 LIONHART LH-501  86H",
    "quantity": ""
  },
  {
    "id": 1091,
    "created": 1560209651797,
    "updated": 1560209651797,
    "deleted": false,
    "modelName": "",
    "brandId": 10,
    "skuId": "LHST5011470010",
    "ourPrice": 29.62,
    "desc": "185/70R14 LIONHART LH-501  88H",
    "quantity": ""
  },
  {
    "id": 1090,
    "created": 1560209651791,
    "updated": 1560209651791,
    "deleted": false,
    "modelName": "",
    "brandId": 10,
    "skuId": "LHST5011465020",
    "ourPrice": 27.2,
    "desc": "185/65R14 LIONHART LH-501  86H",
    "quantity": ""
  },
  {
    "id": 1089,
    "created": 1560209651785,
    "updated": 1560209651785,
    "deleted": false,
    "modelName": "",
    "brandId": 10,
    "skuId": "LHST5011460010",
    "ourPrice": 27.82,
    "desc": "185/60R14 LIONHART LH-501  82H",
    "quantity": ""
  },
  {
    "id": 1088,
    "created": 1560209651779,
    "updated": 1560209651779,
    "deleted": false,
    "modelName": "",
    "brandId": 10,
    "skuId": "LHST5011465010",
    "ourPrice": 26.65,
    "desc": "175/65R14 LIONHART LH-501  84T  XL",
    "quantity": ""
  },
  {
    "id": 1087,
    "created": 1560209651773,
    "updated": 1560209651773,
    "deleted": false,
    "modelName": "",
    "brandId": 10,
    "skuId": "LHS82630020",
    "ourPrice": 97.64,
    "desc": "305/30ZR26 LIONHART LH-EIGHT  109W  XL",
    "quantity": ""
  },
  {
    "id": 1086,
    "created": 1560209651767,
    "updated": 1560209651767,
    "deleted": false,
    "modelName": "",
    "brandId": 10,
    "skuId": "LHS82630010",
    "ourPrice": 93.15,
    "desc": "295/30ZR26 LIONHART LH-EIGHT  107W  XL",
    "quantity": ""
  },
  {
    "id": 1085,
    "created": 1560209651762,
    "updated": 1560209651762,
    "deleted": false,
    "modelName": "",
    "brandId": 10,
    "skuId": "LHS82430040",
    "ourPrice": 83.61,
    "desc": "275/30ZR24 LIONHART LH-EIGHT  101W  XL",
    "quantity": ""
  },
  {
    "id": 1084,
    "created": 1560209651756,
    "updated": 1560209651756,
    "deleted": false,
    "modelName": "",
    "brandId": 10,
    "skuId": "LHS82430010",
    "ourPrice": 81.37,
    "desc": "255/30R24 LIONHART LH-EIGHT  97W  XL",
    "quantity": ""
  },
  {
    "id": 1083,
    "created": 1560209651750,
    "updated": 1560209651750,
    "deleted": false,
    "modelName": "",
    "brandId": 10,
    "skuId": "LHS82225040",
    "ourPrice": 83.05,
    "desc": "295/25ZR22 LIONHART LH-EIGHT  97W  XL",
    "quantity": ""
  },
  {
    "id": 1082,
    "created": 1560209651744,
    "updated": 1560209651744,
    "deleted": false,
    "modelName": "",
    "brandId": 10,
    "skuId": "LHS82230050",
    "ourPrice": 66.78,
    "desc": "265/30ZR22 LIONHART LH-EIGHT  97W  XL",
    "quantity": ""
  },
  {
    "id": 1081,
    "created": 1560209651738,
    "updated": 1560209651738,
    "deleted": false,
    "modelName": "",
    "brandId": 10,
    "skuId": "LHS82230010",
    "ourPrice": 58.36,
    "desc": "255/30R22 LIONHART LH-EIGHT  95W  XL",
    "quantity": ""
  },
  {
    "id": 1080,
    "created": 1560209651732,
    "updated": 1560209651732,
    "deleted": false,
    "modelName": "",
    "brandId": 10,
    "skuId": "LHS42030010",
    "ourPrice": 54.21,
    "desc": "225/30R20 LIONHART LH-FOUR  85W  XL",
    "quantity": ""
  },
  {
    "id": 1079,
    "created": 1560209651726,
    "updated": 1560209651726,
    "deleted": false,
    "modelName": "",
    "brandId": 10,
    "skuId": "LHS4031940010",
    "ourPrice": 133.37,
    "desc": "275/40RF19 LIONHART LH-403RF  101W",
    "quantity": ""
  },
  {
    "id": 1078,
    "created": 1560209651720,
    "updated": 1560209651720,
    "deleted": false,
    "modelName": "",
    "brandId": 10,
    "skuId": "LHS4031945010",
    "ourPrice": 125.04,
    "desc": "245/45ZRF19 LIONHART LH-403RF  98W",
    "quantity": ""
  },
  {
    "id": 1077,
    "created": 1560209651715,
    "updated": 1560209651715,
    "deleted": false,
    "modelName": "",
    "brandId": 10,
    "skuId": "LHS4031850010",
    "ourPrice": 124,
    "desc": "245/50ZRF18 LIONHART LH-403RF  100W",
    "quantity": ""
  },
  {
    "id": 1076,
    "created": 1560209651709,
    "updated": 1560209651709,
    "deleted": false,
    "modelName": "",
    "brandId": 10,
    "skuId": "LHS4031845020",
    "ourPrice": 85.44,
    "desc": "225/45ZRF18 LIONHART LH-403RF  91W",
    "quantity": ""
  },
  {
    "id": 1075,
    "created": 1560209651703,
    "updated": 1560209651703,
    "deleted": false,
    "modelName": "",
    "brandId": 10,
    "skuId": "LHS4031845010",
    "ourPrice": 110.45,
    "desc": "245/45ZRF18 LIONHART LH-403RF  96W",
    "quantity": ""
  },
  {
    "id": 1074,
    "created": 1560209651696,
    "updated": 1560209651696,
    "deleted": false,
    "modelName": "",
    "brandId": 10,
    "skuId": "LHS4031750020",
    "ourPrice": 89.61,
    "desc": "225/50ZRF17 LIONHART LH-403RF  94W",
    "quantity": ""
  },
  {
    "id": 1073,
    "created": 1560209651690,
    "updated": 1560209651690,
    "deleted": false,
    "modelName": "",
    "brandId": 10,
    "skuId": "LHS4031745020",
    "ourPrice": 78.14,
    "desc": "225/45ZRF17 LIONHART LH-403RF  91W",
    "quantity": ""
  },
  {
    "id": 1072,
    "created": 1560209651684,
    "updated": 1560209651684,
    "deleted": false,
    "modelName": "",
    "brandId": 10,
    "skuId": "LHS4031750010",
    "ourPrice": 80.23,
    "desc": "205/50ZRF17 LIONHART LH-403RF  89W",
    "quantity": ""
  },
  {
    "id": 1071,
    "created": 1560209651678,
    "updated": 1560209651678,
    "deleted": false,
    "modelName": "",
    "brandId": 10,
    "skuId": "LHS4031745010",
    "ourPrice": 72.93,
    "desc": "205/45RF17 LIONHART LH-403RF  84W",
    "quantity": ""
  },
  {
    "id": 1070,
    "created": 1560209651672,
    "updated": 1560209651672,
    "deleted": false,
    "modelName": "",
    "brandId": 10,
    "skuId": "LHS4031655020",
    "ourPrice": 75.02,
    "desc": "205/55RF16 LIONHART LH-403RF  91V",
    "quantity": ""
  },
  {
    "id": 1069,
    "created": 1560209651666,
    "updated": 1560209651666,
    "deleted": false,
    "modelName": "",
    "brandId": 10,
    "skuId": "LHS4031655010",
    "ourPrice": 69.8,
    "desc": "195/55RF16 LIONHART LH-403RF  87V",
    "quantity": ""
  },
  {
    "id": 1068,
    "created": 1560209651659,
    "updated": 1560209651659,
    "deleted": false,
    "modelName": "",
    "brandId": 10,
    "skuId": "LHS33030010II",
    "ourPrice": 194.7,
    "desc": "265/30ZR30 LIONHART LH-THREE II  105W  XL",
    "quantity": ""
  },
  {
    "id": 1067,
    "created": 1560209651654,
    "updated": 1560209651654,
    "deleted": false,
    "modelName": "",
    "brandId": 10,
    "skuId": "LHS32835040II",
    "ourPrice": 400,
    "desc": "325/35R28 LIONHART LH-THREE II  120V  XL",
    "quantity": ""
  },
  {
    "id": 1066,
    "created": 1560209651648,
    "updated": 1560209651648,
    "deleted": false,
    "modelName": "",
    "brandId": 10,
    "skuId": "LHS32825010II",
    "ourPrice": 148.81,
    "desc": "295/25ZR28 LIONHART LH-THREE II  103W  XL",
    "quantity": ""
  },
  {
    "id": 1065,
    "created": 1560209651642,
    "updated": 1560209651642,
    "deleted": false,
    "modelName": "",
    "brandId": 10,
    "skuId": "LHS32030060II",
    "ourPrice": 81.24,
    "desc": "285/30R20 LIONHART LH-THREE II  99W  XL",
    "quantity": ""
  },
  {
    "id": 1064,
    "created": 1560209651636,
    "updated": 1560209651636,
    "deleted": false,
    "modelName": "",
    "brandId": 10,
    "skuId": "LHS32035010II",
    "ourPrice": 75.7,
    "desc": "275/35R20 LIONHART LH-THREE II  102W  XL",
    "quantity": ""
  },
  {
    "id": 1063,
    "created": 1560209651630,
    "updated": 1560209651630,
    "deleted": false,
    "modelName": "",
    "brandId": 10,
    "skuId": "LHS32030040II",
    "ourPrice": 66.87,
    "desc": "275/30ZR20 LIONHART LH-THREE II  97W  XL",
    "quantity": ""
  },
  {
    "id": 1062,
    "created": 1560209651625,
    "updated": 1560209651625,
    "deleted": false,
    "modelName": "",
    "brandId": 10,
    "skuId": "LHS32035050II",
    "ourPrice": 61.24,
    "desc": "255/35ZR20 LIONHART LH-THREE II  97W  XL",
    "quantity": ""
  },
  {
    "id": 1061,
    "created": 1560209651619,
    "updated": 1560209651619,
    "deleted": false,
    "modelName": "",
    "brandId": 10,
    "skuId": "LHS32040010II",
    "ourPrice": 72.94,
    "desc": "245/40R20 LIONHART LH-THREE II  99W  XL",
    "quantity": ""
  },
  {
    "id": 1060,
    "created": 1560209651613,
    "updated": 1560209651613,
    "deleted": false,
    "modelName": "",
    "brandId": 10,
    "skuId": "LHS32035020II",
    "ourPrice": 47.4,
    "desc": "245/35ZR20 LIONHART LH-THREE II  95W  XL",
    "quantity": ""
  },
  {
    "id": 1059,
    "created": 1560209651607,
    "updated": 1560209651607,
    "deleted": false,
    "modelName": "",
    "brandId": 10,
    "skuId": "LHS3111755010",
    "ourPrice": 47.51,
    "desc": "215/55ZR17 LIONHART LH-311  98W  XL",
    "quantity": ""
  },
  {
    "id": 1058,
    "created": 1560209651601,
    "updated": 1560209651601,
    "deleted": false,
    "modelName": "",
    "brandId": 10,
    "skuId": "LHS3111655010",
    "ourPrice": 38.39,
    "desc": "205/55R16 LIONHART LH-311  91V",
    "quantity": ""
  },
  {
    "id": 1057,
    "created": 1560209651595,
    "updated": 1560209651595,
    "deleted": false,
    "modelName": "",
    "brandId": 10,
    "skuId": "LHS3111570020",
    "ourPrice": 45.54,
    "desc": "215/70R15 LIONHART LH-311  98 H",
    "quantity": ""
  },
  {
    "id": 1056,
    "created": 1560209651589,
    "updated": 1560209651589,
    "deleted": false,
    "modelName": "",
    "brandId": 10,
    "skuId": "LHS3111570010",
    "ourPrice": 41.58,
    "desc": "205/70R15 LIONHART LH-311  96H",
    "quantity": ""
  },
  {
    "id": 1055,
    "created": 1560209651583,
    "updated": 1560209651583,
    "deleted": false,
    "modelName": "",
    "brandId": 10,
    "skuId": "LHS3111565010",
    "ourPrice": 40.01,
    "desc": "205/65R15 LIONHART LH-311  94V",
    "quantity": ""
  },
  {
    "id": 1054,
    "created": 1560209651577,
    "updated": 1560209651577,
    "deleted": false,
    "modelName": "",
    "brandId": 10,
    "skuId": "LHS3111560010",
    "ourPrice": 33.61,
    "desc": "195/60R15 LIONHART LH-311  88V",
    "quantity": ""
  },
  {
    "id": 1053,
    "created": 1560209651572,
    "updated": 1560209651572,
    "deleted": false,
    "modelName": "",
    "brandId": 10,
    "skuId": "LHS3111550010",
    "ourPrice": 34.65,
    "desc": "195/50R15 LIONHART LH-311  82V",
    "quantity": ""
  },
  {
    "id": 1052,
    "created": 1560209651566,
    "updated": 1560209651566,
    "deleted": false,
    "modelName": "",
    "brandId": 10,
    "skuId": "LHS3031840010",
    "ourPrice": 46.2,
    "desc": "235/40ZR18 LIONHART LH-303  95W  XL",
    "quantity": ""
  },
  {
    "id": 1051,
    "created": 1560209651560,
    "updated": 1560209651560,
    "deleted": false,
    "modelName": "",
    "brandId": 10,
    "skuId": "LHS3031845010",
    "ourPrice": 52.26,
    "desc": "225/45ZR18 LIONHART LH-303  95W  XL",
    "quantity": ""
  },
  {
    "id": 1050,
    "created": 1560209651553,
    "updated": 1560209651553,
    "deleted": false,
    "modelName": "",
    "brandId": 10,
    "skuId": "LHS3031755010",
    "ourPrice": 54.45,
    "desc": "235/55ZR17 LIONHART LH-303  103W  XL",
    "quantity": ""
  },
  {
    "id": 1049,
    "created": 1560209651548,
    "updated": 1560209651548,
    "deleted": false,
    "modelName": "",
    "brandId": 10,
    "skuId": "LHS3031750030",
    "ourPrice": 52.26,
    "desc": "235/50ZR17 LIONHART LH-303  100W  XL",
    "quantity": ""
  },
  {
    "id": 1048,
    "created": 1560209651542,
    "updated": 1560209651542,
    "deleted": false,
    "modelName": "",
    "brandId": 10,
    "skuId": "LHS3031745030",
    "ourPrice": 46.58,
    "desc": "235/45ZR17 LIONHART LH-303  97W  XL",
    "quantity": ""
  },
  {
    "id": 1047,
    "created": 1560209651535,
    "updated": 1560209651535,
    "deleted": false,
    "modelName": "",
    "brandId": 10,
    "skuId": "LHS3031750010",
    "ourPrice": 48.26,
    "desc": "225/50ZR17 LIONHART LH-303  98W  XL",
    "quantity": ""
  },
  {
    "id": 1046,
    "created": 1560209651529,
    "updated": 1560209651529,
    "deleted": false,
    "modelName": "",
    "brandId": 10,
    "skuId": "LHS3031745020",
    "ourPrice": 42.66,
    "desc": "225/45ZR17 LIONHART LH-303  94W  XL",
    "quantity": ""
  },
  {
    "id": 1045,
    "created": 1560209651523,
    "updated": 1560209651523,
    "deleted": false,
    "modelName": "",
    "brandId": 10,
    "skuId": "LHS3031745010",
    "ourPrice": 40.99,
    "desc": "215/45ZR17 LIONHART LH-303  91W  XL",
    "quantity": ""
  },
  {
    "id": 1044,
    "created": 1560209651517,
    "updated": 1560209651517,
    "deleted": false,
    "modelName": "",
    "brandId": 10,
    "skuId": "LHS3031750020",
    "ourPrice": 44.81,
    "desc": "205/50ZR17 LIONHART LH-303  93W  XL",
    "quantity": ""
  },
  {
    "id": 1043,
    "created": 1560209651512,
    "updated": 1560209651512,
    "deleted": false,
    "modelName": "",
    "brandId": 10,
    "skuId": "LHS3031660010",
    "ourPrice": 42.93,
    "desc": "215/60R16 LIONHART LH-303  95V",
    "quantity": ""
  },
  {
    "id": 1042,
    "created": 1560209651505,
    "updated": 1560209651505,
    "deleted": false,
    "modelName": "",
    "brandId": 10,
    "skuId": "LHS3031565010",
    "ourPrice": 36.97,
    "desc": "195/65R15 LIONHART LH-303  91H",
    "quantity": ""
  },
  {
    "id": 1041,
    "created": 1560209651500,
    "updated": 1560209651500,
    "deleted": false,
    "modelName": "",
    "brandId": 10,
    "skuId": "LHS112430010",
    "ourPrice": 117.74,
    "desc": "275/23ZR24 LIONHART LH-ELEVEN  93W  XL",
    "quantity": ""
  },
  {
    "id": 1040,
    "created": 1560209651494,
    "updated": 1560209651494,
    "deleted": false,
    "modelName": "",
    "brandId": 10,
    "skuId": "LHS112425010",
    "ourPrice": 109.34,
    "desc": "255/25ZR24 LIONHART LH-ELEVEN  91W  XL",
    "quantity": ""
  },
  {
    "id": 1039,
    "created": 1560209651488,
    "updated": 1560209651488,
    "deleted": false,
    "modelName": "",
    "brandId": 10,
    "skuId": "LHS112225020",
    "ourPrice": 165.41,
    "desc": "295/25ZR22 LIONHART LH-ELEVEN  97W  XL",
    "quantity": ""
  },
  {
    "id": 1038,
    "created": 1560209651482,
    "updated": 1560209651482,
    "deleted": false,
    "modelName": "",
    "brandId": 10,
    "skuId": "LHS112235010",
    "ourPrice": 97.77,
    "desc": "285/35R22 LIONHART LH-ELEVEN  106W  XL",
    "quantity": ""
  },
  {
    "id": 1037,
    "created": 1560209651476,
    "updated": 1560209651476,
    "deleted": false,
    "modelName": "",
    "brandId": 10,
    "skuId": "LHS112225010",
    "ourPrice": 161.29,
    "desc": "275/25ZR22 LIONHART LH-ELEVEN  93W  XL",
    "quantity": ""
  },
  {
    "id": 1036,
    "created": 1560209651471,
    "updated": 1560209651471,
    "deleted": false,
    "modelName": "",
    "brandId": 10,
    "skuId": "LHS112230040",
    "ourPrice": 138.34,
    "desc": "265/30ZR22 LIONHART LH-ELEVEN  97W  XL",
    "quantity": ""
  },
  {
    "id": 1035,
    "created": 1560209651465,
    "updated": 1560209651465,
    "deleted": false,
    "modelName": "",
    "brandId": 10,
    "skuId": "LHS112225030",
    "ourPrice": 161.29,
    "desc": "265/25ZR22 LIONHART LH-ELEVEN  91W  XL",
    "quantity": ""
  },
  {
    "id": 1034,
    "created": 1560209651459,
    "updated": 1560209651459,
    "deleted": false,
    "modelName": "",
    "brandId": 10,
    "skuId": "LHS112230030",
    "ourPrice": 57.24,
    "desc": "245/30ZR22 LIONHART LH-ELEVEN  92W  XL",
    "quantity": ""
  },
  {
    "id": 1033,
    "created": 1560209651453,
    "updated": 1560209651453,
    "deleted": false,
    "modelName": "",
    "brandId": 10,
    "skuId": "LHS112230020",
    "ourPrice": 56.93,
    "desc": "235/30ZR22 LIONHART LH-ELEVEN  90W  XL",
    "quantity": ""
  },
  {
    "id": 1032,
    "created": 1560209651447,
    "updated": 1560209651447,
    "deleted": false,
    "modelName": "",
    "brandId": 10,
    "skuId": "LHS112230010",
    "ourPrice": 55,
    "desc": "225/30ZR22 LIONHART LH-ELEVEN  87W  XL",
    "quantity": ""
  },
  {
    "id": 1031,
    "created": 1560209651441,
    "updated": 1560209651441,
    "deleted": false,
    "modelName": "",
    "brandId": 10,
    "skuId": "LHQHTS1765060",
    "ourPrice": 74.28,
    "desc": "P275/65R17 LIONHART LH-HTS  113T",
    "quantity": ""
  },
  {
    "id": 1030,
    "created": 1560209651436,
    "updated": 1560209651436,
    "deleted": false,
    "modelName": "",
    "brandId": 10,
    "skuId": "LHQ0021945010",
    "ourPrice": 78.2,
    "desc": "275/45ZR19 LIONHART LH-002  104W  XL",
    "quantity": ""
  },
  {
    "id": 1029,
    "created": 1560209651430,
    "updated": 1560209651430,
    "deleted": false,
    "modelName": "",
    "brandId": 10,
    "skuId": "LHQ0021955020",
    "ourPrice": 77.21,
    "desc": "255/55ZR19 LIONHART LH-002  107W",
    "quantity": ""
  },
  {
    "id": 1028,
    "created": 1560209651424,
    "updated": 1560209651424,
    "deleted": false,
    "modelName": "",
    "brandId": 10,
    "skuId": "LHQ0011565040",
    "ourPrice": 39.75,
    "desc": "215/65R15 LIONHART LH-001  96H",
    "quantity": ""
  },
  {
    "id": 1027,
    "created": 1560209651417,
    "updated": 1560209651417,
    "deleted": false,
    "modelName": "",
    "brandId": 10,
    "skuId": "LHQ0011460020",
    "ourPrice": 31.29,
    "desc": "195/60R14 LIONHART LH-001  86H",
    "quantity": ""
  },
  {
    "id": 1026,
    "created": 1560209651412,
    "updated": 1560209651412,
    "deleted": false,
    "modelName": "",
    "brandId": 10,
    "skuId": "LHQ0011460010",
    "ourPrice": 28.16,
    "desc": "185/60R14 LIONHART LH-001  82H",
    "quantity": ""
  },
  {
    "id": 1025,
    "created": 1560209651406,
    "updated": 1560209651406,
    "deleted": false,
    "modelName": "",
    "brandId": 10,
    "skuId": "LHGHTP1605",
    "ourPrice": 60,
    "desc": "P245/70R16 LIONHART LH-HTP  106T",
    "quantity": ""
  },
  {
    "id": 1024,
    "created": 1560209651400,
    "updated": 1560209651400,
    "deleted": false,
    "modelName": "",
    "brandId": 10,
    "skuId": "LHGHTP1609",
    "ourPrice": 60,
    "desc": "P225/75R16 LIONHART LH-HTP  104T",
    "quantity": ""
  },
  {
    "id": 1023,
    "created": 1560209651394,
    "updated": 1560209651394,
    "deleted": false,
    "modelName": "",
    "brandId": 10,
    "skuId": "LHGHTP1503",
    "ourPrice": 53,
    "desc": "215/75R15 LIONHART LH-HTP  100T",
    "quantity": ""
  },
  {
    "id": 1022,
    "created": 1560209651388,
    "updated": 1560209651388,
    "deleted": false,
    "modelName": "",
    "brandId": 10,
    "skuId": "LHGCTS1402",
    "ourPrice": 48.14,
    "desc": "195R14C LIONHART LH-CTS  106/104Q",
    "quantity": ""
  },
  {
    "id": 1021,
    "created": 1560209651383,
    "updated": 1560209651383,
    "deleted": false,
    "modelName": "",
    "brandId": 10,
    "skuId": "LHG4041601",
    "ourPrice": 100,
    "desc": "205/65R16 LIONHART LH-404  95T",
    "quantity": ""
  },
  {
    "id": 1020,
    "created": 1560209651377,
    "updated": 1560209651377,
    "deleted": false,
    "modelName": "",
    "brandId": 10,
    "skuId": "LHG4041506",
    "ourPrice": 90,
    "desc": "205/65R15 LIONHART LH-404  94V",
    "quantity": ""
  },
  {
    "id": 1019,
    "created": 1560209651371,
    "updated": 1560209651371,
    "deleted": false,
    "modelName": "",
    "brandId": 10,
    "skuId": "LHG4041505",
    "ourPrice": 34,
    "desc": "205/60R15 LIONHART LH-404  91H",
    "quantity": ""
  },
  {
    "id": 1018,
    "created": 1560209651365,
    "updated": 1560209651365,
    "deleted": false,
    "modelName": "",
    "brandId": 10,
    "skuId": "LHG3031501",
    "ourPrice": 100,
    "desc": "205/70R15 LIONHART LH-303  96T",
    "quantity": ""
  },
  {
    "id": 1017,
    "created": 1560209651359,
    "updated": 1560209651359,
    "deleted": false,
    "modelName": "",
    "brandId": 10,
    "skuId": "LHG3031406",
    "ourPrice": 36,
    "desc": "205/70R14 LIONHART LH-303  98T",
    "quantity": ""
  },
  {
    "id": 1016,
    "created": 1560209651353,
    "updated": 1560209651353,
    "deleted": false,
    "modelName": "",
    "brandId": 10,
    "skuId": "LHG3031402",
    "ourPrice": 29,
    "desc": "185/60R14 LIONHART LH-303  82H",
    "quantity": ""
  },
  {
    "id": 1015,
    "created": 1560209651348,
    "updated": 1560209651348,
    "deleted": false,
    "modelName": "",
    "brandId": 10,
    "skuId": "LHG3031404",
    "ourPrice": 24,
    "desc": "175/65R14 LIONHART LH-303  82T",
    "quantity": ""
  },
  {
    "id": 1014,
    "created": 1560209651342,
    "updated": 1560209651342,
    "deleted": false,
    "modelName": "",
    "brandId": 10,
    "skuId": "LHG2021710",
    "ourPrice": 46.99,
    "desc": "215/40R17 LIONHART LH-202  83W",
    "quantity": ""
  },
  {
    "id": 1013,
    "created": 1560209651336,
    "updated": 1560209651336,
    "deleted": false,
    "modelName": "",
    "brandId": 10,
    "skuId": "LHG1011602",
    "ourPrice": 46,
    "desc": "225/55ZR16 LIONHART LH-101  99W  XL",
    "quantity": ""
  }
]